[{"bransKodu":"701","bransAd":"YANGIN","ay":1,"vadeGun":362.382533},{"bransKodu":"701","bransAd":"YANGIN","ay":2,"vadeGun":364.288947},{"bransKodu":"701","bransAd":"YANGIN","ay":3,"vadeGun":362.860584},{"bransKodu":"701","bransAd":"YANGIN","ay":4,"vadeGun":363.220729},{"bransKodu":"701","bransAd":"YANGIN","ay":5,"vadeGun":360.872435},{"bransKodu":"701","bransAd":"YANGIN","ay":6,"vadeGun":361.61592},{"bransKodu":"701","bransAd":"YANGIN","ay":7,"vadeGun":364.034791},{"bransKodu":"701","bransAd":"YANGIN","ay":8,"vadeGun":362.95463},{"bransKodu":"701","bransAd":"YANGIN","ay":9,"vadeGun":359.396007},{"bransKodu":"701","bransAd":"YANGIN","ay":10,"vadeGun":359.022379},{"bransKodu":"701","bransAd":"YANGIN","ay":11,"vadeGun":360.602985},{"bransKodu":"701","bransAd":"YANGIN","ay":12,"vadeGun":360.548169},{"bransKodu":"702","bransAd":"KAR KAYBI","ay":1,"vadeGun":360.871508},{"bransKodu":"702","bransAd":"KAR KAYBI","ay":2,"vadeGun":352.840897},{"bransKodu":"702","bransAd":"KAR KAYBI","ay":3,"vadeGun":364.084421},{"bransKodu":"702","bransAd":"KAR KAYBI","ay":4,"vadeGun":346.672441},{"bransKodu":"702","bransAd":"KAR KAYBI","ay":5,"vadeGun":315.735736},{"bransKodu":"702","bransAd":"KAR KAYBI","ay":6,"vadeGun":365.333333},{"bransKodu":"702","bransAd":"KAR KAYBI","ay":7,"vadeGun":347.029233},{"bransKodu":"702","bransAd":"KAR KAYBI","ay":8,"vadeGun":359.148148},{"bransKodu":"702","bransAd":"KAR KAYBI","ay":9,"vadeGun":349.12},{"bransKodu":"702","bransAd":"KAR KAYBI","ay":10,"vadeGun":342.160494},{"bransKodu":"702","bransAd":"KAR KAYBI","ay":11,"vadeGun":340.930719},{"bransKodu":"702","bransAd":"KAR KAYBI","ay":12,"vadeGun":359.228565},{"bransKodu":"703","bransAd":"ZORUNLU DEPREM (DASK)","ay":1,"vadeGun":365.333249},{"bransKodu":"703","bransAd":"ZORUNLU DEPREM (DASK)","ay":2,"vadeGun":365.326227},{"bransKodu":"703","bransAd":"ZORUNLU DEPREM (DASK)","ay":3,"vadeGun":365.332881},{"bransKodu":"703","bransAd":"ZORUNLU DEPREM (DASK)","ay":4,"vadeGun":365.333333},{"bransKodu":"703","bransAd":"ZORUNLU DEPREM (DASK)","ay":5,"vadeGun":365.333333},{"bransKodu":"703","bransAd":"ZORUNLU DEPREM (DASK)","ay":6,"vadeGun":365.333333},{"bransKodu":"703","bransAd":"ZORUNLU DEPREM (DASK)","ay":7,"vadeGun":365.333333},{"bransKodu":"703","bransAd":"ZORUNLU DEPREM (DASK)","ay":8,"vadeGun":365.333333},{"bransKodu":"703","bransAd":"ZORUNLU DEPREM (DASK)","ay":9,"vadeGun":365.333333},{"bransKodu":"703","bransAd":"ZORUNLU DEPREM (DASK)","ay":10,"vadeGun":365.333333},{"bransKodu":"703","bransAd":"ZORUNLU DEPREM (DASK)","ay":11,"vadeGun":365.273403},{"bransKodu":"703","bransAd":"ZORUNLU DEPREM (DASK)","ay":12,"vadeGun":365.333291},{"bransKodu":"704","bransAd":"MADEN ÇALIŞANLARI ZORUNLU FERDİ KAZA","ay":1,"vadeGun":365},{"bransKodu":"704","bransAd":"MADEN ÇALIŞANLARI ZORUNLU FERDİ KAZA","ay":2,"vadeGun":365},{"bransKodu":"704","bransAd":"MADEN ÇALIŞANLARI ZORUNLU FERDİ KAZA","ay":3,"vadeGun":365},{"bransKodu":"704","bransAd":"MADEN ÇALIŞANLARI ZORUNLU FERDİ KAZA","ay":4,"vadeGun":365},{"bransKodu":"704","bransAd":"MADEN ÇALIŞANLARI ZORUNLU FERDİ KAZA","ay":5,"vadeGun":365},{"bransKodu":"704","bransAd":"MADEN ÇALIŞANLARI ZORUNLU FERDİ KAZA","ay":6,"vadeGun":365},{"bransKodu":"704","bransAd":"MADEN ÇALIŞANLARI ZORUNLU FERDİ KAZA","ay":7,"vadeGun":365},{"bransKodu":"704","bransAd":"MADEN ÇALIŞANLARI ZORUNLU FERDİ KAZA","ay":8,"vadeGun":365.5},{"bransKodu":"704","bransAd":"MADEN ÇALIŞANLARI ZORUNLU FERDİ KAZA","ay":9,"vadeGun":365},{"bransKodu":"704","bransAd":"MADEN ÇALIŞANLARI ZORUNLU FERDİ KAZA","ay":10,"vadeGun":365},{"bransKodu":"704","bransAd":"MADEN ÇALIŞANLARI ZORUNLU FERDİ KAZA","ay":11,"vadeGun":365},{"bransKodu":"704","bransAd":"MADEN ÇALIŞANLARI ZORUNLU FERDİ KAZA","ay":12,"vadeGun":365.5},{"bransKodu":"705","bransAd":"DOĞRUDAN KEFALET","ay":1,"vadeGun":834.640117},{"bransKodu":"705","bransAd":"DOĞRUDAN KEFALET","ay":2,"vadeGun":1151.864241},{"bransKodu":"705","bransAd":"DOĞRUDAN KEFALET","ay":3,"vadeGun":1129.150445},{"bransKodu":"705","bransAd":"DOĞRUDAN KEFALET","ay":4,"vadeGun":834.770615},{"bransKodu":"705","bransAd":"DOĞRUDAN KEFALET","ay":5,"vadeGun":976.952098},{"bransKodu":"705","bransAd":"DOĞRUDAN KEFALET","ay":6,"vadeGun":906.651057},{"bransKodu":"705","bransAd":"DOĞRUDAN KEFALET","ay":7,"vadeGun":916.763754},{"bransKodu":"705","bransAd":"DOĞRUDAN KEFALET","ay":8,"vadeGun":967.247463},{"bransKodu":"705","bransAd":"DOĞRUDAN KEFALET","ay":9,"vadeGun":902.103378},{"bransKodu":"705","bransAd":"DOĞRUDAN KEFALET","ay":10,"vadeGun":705.473526},{"bransKodu":"705","bransAd":"DOĞRUDAN KEFALET","ay":11,"vadeGun":603.65337},{"bransKodu":"705","bransAd":"DOĞRUDAN KEFALET","ay":12,"vadeGun":603.382697},{"bransKodu":"706","bransAd":"DOLAYLI KEFALET","ay":1,"vadeGun":365},{"bransKodu":"706","bransAd":"DOLAYLI KEFALET","ay":2,"vadeGun":365},{"bransKodu":"706","bransAd":"DOLAYLI KEFALET","ay":3,"vadeGun":365},{"bransKodu":"706","bransAd":"DOLAYLI KEFALET","ay":4,"vadeGun":365},{"bransKodu":"706","bransAd":"DOLAYLI KEFALET","ay":5,"vadeGun":365},{"bransKodu":"706","bransAd":"DOLAYLI KEFALET","ay":6,"vadeGun":365},{"bransKodu":"706","bransAd":"DOLAYLI KEFALET","ay":7,"vadeGun":365},{"bransKodu":"706","bransAd":"DOLAYLI KEFALET","ay":8,"vadeGun":365},{"bransKodu":"706","bransAd":"DOLAYLI KEFALET","ay":9,"vadeGun":365},{"bransKodu":"706","bransAd":"DOLAYLI KEFALET","ay":10,"vadeGun":365},{"bransKodu":"706","bransAd":"DOLAYLI KEFALET","ay":11,"vadeGun":365},{"bransKodu":"706","bransAd":"DOLAYLI KEFALET","ay":12,"vadeGun":365},{"bransKodu":"707","bransAd":"DEVLET DESTEKLİ TİCARİ ALACAK SİGORTASI","ay":1,"vadeGun":365},{"bransKodu":"707","bransAd":"DEVLET DESTEKLİ TİCARİ ALACAK SİGORTASI","ay":2,"vadeGun":366},{"bransKodu":"707","bransAd":"DEVLET DESTEKLİ TİCARİ ALACAK SİGORTASI","ay":3,"vadeGun":365},{"bransKodu":"707","bransAd":"DEVLET DESTEKLİ TİCARİ ALACAK SİGORTASI","ay":4,"vadeGun":365},{"bransKodu":"707","bransAd":"DEVLET DESTEKLİ TİCARİ ALACAK SİGORTASI","ay":5,"vadeGun":365},{"bransKodu":"707","bransAd":"DEVLET DESTEKLİ TİCARİ ALACAK SİGORTASI","ay":6,"vadeGun":365.5},{"bransKodu":"707","bransAd":"DEVLET DESTEKLİ TİCARİ ALACAK SİGORTASI","ay":7,"vadeGun":365},{"bransKodu":"707","bransAd":"DEVLET DESTEKLİ TİCARİ ALACAK SİGORTASI","ay":8,"vadeGun":365},{"bransKodu":"707","bransAd":"DEVLET DESTEKLİ TİCARİ ALACAK SİGORTASI","ay":9,"vadeGun":365},{"bransKodu":"707","bransAd":"DEVLET DESTEKLİ TİCARİ ALACAK SİGORTASI","ay":10,"vadeGun":365},{"bransKodu":"707","bransAd":"DEVLET DESTEKLİ TİCARİ ALACAK SİGORTASI","ay":11,"vadeGun":365},{"bransKodu":"707","bransAd":"DEVLET DESTEKLİ TİCARİ ALACAK SİGORTASI","ay":12,"vadeGun":365.5},{"bransKodu":"708","bransAd":"BİNA TAMAMLAMA","ay":1,"vadeGun":365},{"bransKodu":"708","bransAd":"BİNA TAMAMLAMA","ay":2,"vadeGun":365},{"bransKodu":"708","bransAd":"BİNA TAMAMLAMA","ay":3,"vadeGun":365},{"bransKodu":"708","bransAd":"BİNA TAMAMLAMA","ay":4,"vadeGun":365},{"bransKodu":"708","bransAd":"BİNA TAMAMLAMA","ay":5,"vadeGun":365},{"bransKodu":"708","bransAd":"BİNA TAMAMLAMA","ay":6,"vadeGun":365},{"bransKodu":"708","bransAd":"BİNA TAMAMLAMA","ay":7,"vadeGun":365},{"bransKodu":"708","bransAd":"BİNA TAMAMLAMA","ay":8,"vadeGun":365},{"bransKodu":"708","bransAd":"BİNA TAMAMLAMA","ay":9,"vadeGun":365},{"bransKodu":"708","bransAd":"BİNA TAMAMLAMA","ay":10,"vadeGun":365},{"bransKodu":"708","bransAd":"BİNA TAMAMLAMA","ay":11,"vadeGun":365},{"bransKodu":"708","bransAd":"BİNA TAMAMLAMA","ay":12,"vadeGun":365},{"bransKodu":"710","bransAd":"EMTEA","ay":1,"vadeGun":198.234699},{"bransKodu":"710","bransAd":"EMTEA","ay":2,"vadeGun":192.031796},{"bransKodu":"710","bransAd":"EMTEA","ay":3,"vadeGun":180.308909},{"bransKodu":"710","bransAd":"EMTEA","ay":4,"vadeGun":178.044552},{"bransKodu":"710","bransAd":"EMTEA","ay":5,"vadeGun":188.205745},{"bransKodu":"710","bransAd":"EMTEA","ay":6,"vadeGun":184.071105},{"bransKodu":"710","bransAd":"EMTEA","ay":7,"vadeGun":170.757922},{"bransKodu":"710","bransAd":"EMTEA","ay":8,"vadeGun":212.241885},{"bransKodu":"710","bransAd":"EMTEA","ay":9,"vadeGun":207.004901},{"bransKodu":"710","bransAd":"EMTEA","ay":10,"vadeGun":196.876053},{"bransKodu":"710","bransAd":"EMTEA","ay":11,"vadeGun":190.033314},{"bransKodu":"710","bransAd":"EMTEA","ay":12,"vadeGun":229.614435},{"bransKodu":"711","bransAd":"KIYMET","ay":1,"vadeGun":365},{"bransKodu":"711","bransAd":"KIYMET","ay":2,"vadeGun":365},{"bransKodu":"711","bransAd":"KIYMET","ay":3,"vadeGun":365},{"bransKodu":"711","bransAd":"KIYMET","ay":4,"vadeGun":365},{"bransKodu":"711","bransAd":"KIYMET","ay":5,"vadeGun":365},{"bransKodu":"711","bransAd":"KIYMET","ay":6,"vadeGun":365},{"bransKodu":"711","bransAd":"KIYMET","ay":7,"vadeGun":365},{"bransKodu":"711","bransAd":"KIYMET","ay":8,"vadeGun":365},{"bransKodu":"711","bransAd":"KIYMET","ay":9,"vadeGun":365},{"bransKodu":"711","bransAd":"KIYMET","ay":10,"vadeGun":365},{"bransKodu":"711","bransAd":"KIYMET","ay":11,"vadeGun":365},{"bransKodu":"711","bransAd":"KIYMET","ay":12,"vadeGun":365},{"bransKodu":"712","bransAd":"TEKNE","ay":1,"vadeGun":365},{"bransKodu":"712","bransAd":"TEKNE","ay":2,"vadeGun":365.333333},{"bransKodu":"712","bransAd":"TEKNE","ay":3,"vadeGun":365.291667},{"bransKodu":"712","bransAd":"TEKNE","ay":4,"vadeGun":365.333333},{"bransKodu":"712","bransAd":"TEKNE","ay":5,"vadeGun":365.333333},{"bransKodu":"712","bransAd":"TEKNE","ay":6,"vadeGun":365.333333},{"bransKodu":"712","bransAd":"TEKNE","ay":7,"vadeGun":362.692308},{"bransKodu":"712","bransAd":"TEKNE","ay":8,"vadeGun":365.333333},{"bransKodu":"712","bransAd":"TEKNE","ay":9,"vadeGun":365.5},{"bransKodu":"712","bransAd":"TEKNE","ay":10,"vadeGun":365.333333},{"bransKodu":"712","bransAd":"TEKNE","ay":11,"vadeGun":365.333333},{"bransKodu":"712","bransAd":"TEKNE","ay":12,"vadeGun":364.54902},{"bransKodu":"713","bransAd":"RAYLI ARAÇLAR GENEL","ay":1,"vadeGun":365},{"bransKodu":"713","bransAd":"RAYLI ARAÇLAR GENEL","ay":2,"vadeGun":365},{"bransKodu":"713","bransAd":"RAYLI ARAÇLAR GENEL","ay":3,"vadeGun":365},{"bransKodu":"713","bransAd":"RAYLI ARAÇLAR GENEL","ay":4,"vadeGun":365},{"bransKodu":"713","bransAd":"RAYLI ARAÇLAR GENEL","ay":5,"vadeGun":365},{"bransKodu":"713","bransAd":"RAYLI ARAÇLAR GENEL","ay":6,"vadeGun":365},{"bransKodu":"713","bransAd":"RAYLI ARAÇLAR GENEL","ay":7,"vadeGun":365},{"bransKodu":"713","bransAd":"RAYLI ARAÇLAR GENEL","ay":8,"vadeGun":365},{"bransKodu":"713","bransAd":"RAYLI ARAÇLAR GENEL","ay":9,"vadeGun":365},{"bransKodu":"713","bransAd":"RAYLI ARAÇLAR GENEL","ay":10,"vadeGun":365},{"bransKodu":"713","bransAd":"RAYLI ARAÇLAR GENEL","ay":11,"vadeGun":365},{"bransKodu":"713","bransAd":"RAYLI ARAÇLAR GENEL","ay":12,"vadeGun":365},{"bransKodu":"714","bransAd":"ZORUNLU KARAYOLU TAŞIMACILIK MALİ SORUMLULUK","ay":1,"vadeGun":365},{"bransKodu":"714","bransAd":"ZORUNLU KARAYOLU TAŞIMACILIK MALİ SORUMLULUK","ay":2,"vadeGun":365},{"bransKodu":"714","bransAd":"ZORUNLU KARAYOLU TAŞIMACILIK MALİ SORUMLULUK","ay":3,"vadeGun":365},{"bransKodu":"714","bransAd":"ZORUNLU KARAYOLU TAŞIMACILIK MALİ SORUMLULUK","ay":4,"vadeGun":365},{"bransKodu":"714","bransAd":"ZORUNLU KARAYOLU TAŞIMACILIK MALİ SORUMLULUK","ay":5,"vadeGun":365},{"bransKodu":"714","bransAd":"ZORUNLU KARAYOLU TAŞIMACILIK MALİ SORUMLULUK","ay":6,"vadeGun":365},{"bransKodu":"714","bransAd":"ZORUNLU KARAYOLU TAŞIMACILIK MALİ SORUMLULUK","ay":7,"vadeGun":365},{"bransKodu":"714","bransAd":"ZORUNLU KARAYOLU TAŞIMACILIK MALİ SORUMLULUK","ay":8,"vadeGun":365},{"bransKodu":"714","bransAd":"ZORUNLU KARAYOLU TAŞIMACILIK MALİ SORUMLULUK","ay":9,"vadeGun":365},{"bransKodu":"714","bransAd":"ZORUNLU KARAYOLU TAŞIMACILIK MALİ SORUMLULUK","ay":10,"vadeGun":365},{"bransKodu":"714","bransAd":"ZORUNLU KARAYOLU TAŞIMACILIK MALİ SORUMLULUK","ay":11,"vadeGun":365},{"bransKodu":"714","bransAd":"ZORUNLU KARAYOLU TAŞIMACILIK MALİ SORUMLULUK","ay":12,"vadeGun":365},{"bransKodu":"715","bransAd":"ZORUNLU TRAFİK","ay":1,"vadeGun":365.31394},{"bransKodu":"715","bransAd":"ZORUNLU TRAFİK","ay":2,"vadeGun":365.305688},{"bransKodu":"715","bransAd":"ZORUNLU TRAFİK","ay":3,"vadeGun":364.821829},{"bransKodu":"715","bransAd":"ZORUNLU TRAFİK","ay":4,"vadeGun":363.639182},{"bransKodu":"715","bransAd":"ZORUNLU TRAFİK","ay":5,"vadeGun":362.726984},{"bransKodu":"715","bransAd":"ZORUNLU TRAFİK","ay":6,"vadeGun":354.221344},{"bransKodu":"715","bransAd":"ZORUNLU TRAFİK","ay":7,"vadeGun":352.56023},{"bransKodu":"715","bransAd":"ZORUNLU TRAFİK","ay":8,"vadeGun":361.798544},{"bransKodu":"715","bransAd":"ZORUNLU TRAFİK","ay":9,"vadeGun":363.042541},{"bransKodu":"715","bransAd":"ZORUNLU TRAFİK","ay":10,"vadeGun":364.455347},{"bransKodu":"715","bransAd":"ZORUNLU TRAFİK","ay":11,"vadeGun":364.844411},{"bransKodu":"715","bransAd":"ZORUNLU TRAFİK","ay":12,"vadeGun":365.001299},{"bransKodu":"716","bransAd":"MOTORLU KARA TAŞIT ARAÇLARI İHTİYARİ MALİ SORUMLULUK","ay":1,"vadeGun":364.142122},{"bransKodu":"716","bransAd":"MOTORLU KARA TAŞIT ARAÇLARI İHTİYARİ MALİ SORUMLULUK","ay":2,"vadeGun":365.075546},{"bransKodu":"716","bransAd":"MOTORLU KARA TAŞIT ARAÇLARI İHTİYARİ MALİ SORUMLULUK","ay":3,"vadeGun":364.342162},{"bransKodu":"716","bransAd":"MOTORLU KARA TAŞIT ARAÇLARI İHTİYARİ MALİ SORUMLULUK","ay":4,"vadeGun":363.051303},{"bransKodu":"716","bransAd":"MOTORLU KARA TAŞIT ARAÇLARI İHTİYARİ MALİ SORUMLULUK","ay":5,"vadeGun":361.9826},{"bransKodu":"716","bransAd":"MOTORLU KARA TAŞIT ARAÇLARI İHTİYARİ MALİ SORUMLULUK","ay":6,"vadeGun":354.173219},{"bransKodu":"716","bransAd":"MOTORLU KARA TAŞIT ARAÇLARI İHTİYARİ MALİ SORUMLULUK","ay":7,"vadeGun":354.016164},{"bransKodu":"716","bransAd":"MOTORLU KARA TAŞIT ARAÇLARI İHTİYARİ MALİ SORUMLULUK","ay":8,"vadeGun":361.107269},{"bransKodu":"716","bransAd":"MOTORLU KARA TAŞIT ARAÇLARI İHTİYARİ MALİ SORUMLULUK","ay":9,"vadeGun":361.019397},{"bransKodu":"716","bransAd":"MOTORLU KARA TAŞIT ARAÇLARI İHTİYARİ MALİ SORUMLULUK","ay":10,"vadeGun":362.847634},{"bransKodu":"716","bransAd":"MOTORLU KARA TAŞIT ARAÇLARI İHTİYARİ MALİ SORUMLULUK","ay":11,"vadeGun":363.755897},{"bransKodu":"716","bransAd":"MOTORLU KARA TAŞIT ARAÇLARI İHTİYARİ MALİ SORUMLULUK","ay":12,"vadeGun":364.421499},{"bransKodu":"717","bransAd":"MOTORLU KARA TAŞIT ARAÇLARI KASKO","ay":1,"vadeGun":360.69339},{"bransKodu":"717","bransAd":"MOTORLU KARA TAŞIT ARAÇLARI KASKO","ay":2,"vadeGun":363.690952},{"bransKodu":"717","bransAd":"MOTORLU KARA TAŞIT ARAÇLARI KASKO","ay":3,"vadeGun":362.762576},{"bransKodu":"717","bransAd":"MOTORLU KARA TAŞIT ARAÇLARI KASKO","ay":4,"vadeGun":360.35139},{"bransKodu":"717","bransAd":"MOTORLU KARA TAŞIT ARAÇLARI KASKO","ay":5,"vadeGun":362.228137},{"bransKodu":"717","bransAd":"MOTORLU KARA TAŞIT ARAÇLARI KASKO","ay":6,"vadeGun":362.6853},{"bransKodu":"717","bransAd":"MOTORLU KARA TAŞIT ARAÇLARI KASKO","ay":7,"vadeGun":363.654492},{"bransKodu":"717","bransAd":"MOTORLU KARA TAŞIT ARAÇLARI KASKO","ay":8,"vadeGun":362.618958},{"bransKodu":"717","bransAd":"MOTORLU KARA TAŞIT ARAÇLARI KASKO","ay":9,"vadeGun":359.499219},{"bransKodu":"717","bransAd":"MOTORLU KARA TAŞIT ARAÇLARI KASKO","ay":10,"vadeGun":359.60889},{"bransKodu":"717","bransAd":"MOTORLU KARA TAŞIT ARAÇLARI KASKO","ay":11,"vadeGun":357.819317},{"bransKodu":"717","bransAd":"MOTORLU KARA TAŞIT ARAÇLARI KASKO","ay":12,"vadeGun":362.554606},{"bransKodu":"718","bransAd":"OTOBÜS ZORUNLU KOLTUK FERDİ KAZA","ay":1,"vadeGun":365},{"bransKodu":"718","bransAd":"OTOBÜS ZORUNLU KOLTUK FERDİ KAZA","ay":2,"vadeGun":365},{"bransKodu":"718","bransAd":"OTOBÜS ZORUNLU KOLTUK FERDİ KAZA","ay":3,"vadeGun":365},{"bransKodu":"718","bransAd":"OTOBÜS ZORUNLU KOLTUK FERDİ KAZA","ay":4,"vadeGun":365},{"bransKodu":"718","bransAd":"OTOBÜS ZORUNLU KOLTUK FERDİ KAZA","ay":5,"vadeGun":365},{"bransKodu":"718","bransAd":"OTOBÜS ZORUNLU KOLTUK FERDİ KAZA","ay":6,"vadeGun":365},{"bransKodu":"718","bransAd":"OTOBÜS ZORUNLU KOLTUK FERDİ KAZA","ay":7,"vadeGun":365},{"bransKodu":"718","bransAd":"OTOBÜS ZORUNLU KOLTUK FERDİ KAZA","ay":8,"vadeGun":365},{"bransKodu":"718","bransAd":"OTOBÜS ZORUNLU KOLTUK FERDİ KAZA","ay":9,"vadeGun":365},{"bransKodu":"718","bransAd":"OTOBÜS ZORUNLU KOLTUK FERDİ KAZA","ay":10,"vadeGun":365},{"bransKodu":"718","bransAd":"OTOBÜS ZORUNLU KOLTUK FERDİ KAZA","ay":11,"vadeGun":365},{"bransKodu":"718","bransAd":"OTOBÜS ZORUNLU KOLTUK FERDİ KAZA","ay":12,"vadeGun":365},{"bransKodu":"719","bransAd":"İŞVEREN MALİ SORUMLULUK","ay":1,"vadeGun":351.391858},{"bransKodu":"719","bransAd":"İŞVEREN MALİ SORUMLULUK","ay":2,"vadeGun":359.233567},{"bransKodu":"719","bransAd":"İŞVEREN MALİ SORUMLULUK","ay":3,"vadeGun":339.793356},{"bransKodu":"719","bransAd":"İŞVEREN MALİ SORUMLULUK","ay":4,"vadeGun":329.296828},{"bransKodu":"719","bransAd":"İŞVEREN MALİ SORUMLULUK","ay":5,"vadeGun":327.892229},{"bransKodu":"719","bransAd":"İŞVEREN MALİ SORUMLULUK","ay":6,"vadeGun":336.306071},{"bransKodu":"719","bransAd":"İŞVEREN MALİ SORUMLULUK","ay":7,"vadeGun":329.923647},{"bransKodu":"719","bransAd":"İŞVEREN MALİ SORUMLULUK","ay":8,"vadeGun":328.322956},{"bransKodu":"719","bransAd":"İŞVEREN MALİ SORUMLULUK","ay":9,"vadeGun":311.041133},{"bransKodu":"719","bransAd":"İŞVEREN MALİ SORUMLULUK","ay":10,"vadeGun":303.995066},{"bransKodu":"719","bransAd":"İŞVEREN MALİ SORUMLULUK","ay":11,"vadeGun":311.535664},{"bransKodu":"719","bransAd":"İŞVEREN MALİ SORUMLULUK","ay":12,"vadeGun":303.622606},{"bransKodu":"720","bransAd":"ÜÇÜNCÜ ŞAHISLARA KARŞI MALİ SORUMLULUK","ay":1,"vadeGun":358.175427},{"bransKodu":"720","bransAd":"ÜÇÜNCÜ ŞAHISLARA KARŞI MALİ SORUMLULUK","ay":2,"vadeGun":363.061407},{"bransKodu":"720","bransAd":"ÜÇÜNCÜ ŞAHISLARA KARŞI MALİ SORUMLULUK","ay":3,"vadeGun":360.500061},{"bransKodu":"720","bransAd":"ÜÇÜNCÜ ŞAHISLARA KARŞI MALİ SORUMLULUK","ay":4,"vadeGun":360.184132},{"bransKodu":"720","bransAd":"ÜÇÜNCÜ ŞAHISLARA KARŞI MALİ SORUMLULUK","ay":5,"vadeGun":357.100288},{"bransKodu":"720","bransAd":"ÜÇÜNCÜ ŞAHISLARA KARŞI MALİ SORUMLULUK","ay":6,"vadeGun":359.475515},{"bransKodu":"720","bransAd":"ÜÇÜNCÜ ŞAHISLARA KARŞI MALİ SORUMLULUK","ay":7,"vadeGun":360.778502},{"bransKodu":"720","bransAd":"ÜÇÜNCÜ ŞAHISLARA KARŞI MALİ SORUMLULUK","ay":8,"vadeGun":359.557025},{"bransKodu":"720","bransAd":"ÜÇÜNCÜ ŞAHISLARA KARŞI MALİ SORUMLULUK","ay":9,"vadeGun":351.648404},{"bransKodu":"720","bransAd":"ÜÇÜNCÜ ŞAHISLARA KARŞI MALİ SORUMLULUK","ay":10,"vadeGun":349.655488},{"bransKodu":"720","bransAd":"ÜÇÜNCÜ ŞAHISLARA KARŞI MALİ SORUMLULUK","ay":11,"vadeGun":353.011393},{"bransKodu":"720","bransAd":"ÜÇÜNCÜ ŞAHISLARA KARŞI MALİ SORUMLULUK","ay":12,"vadeGun":352.190169},{"bransKodu":"721","bransAd":"ASANSÖR KAZA ÜÇÜNCÜ ŞAHISLARA KARŞI MALİ SORUMLULUK","ay":1,"vadeGun":365},{"bransKodu":"721","bransAd":"ASANSÖR KAZA ÜÇÜNCÜ ŞAHISLARA KARŞI MALİ SORUMLULUK","ay":2,"vadeGun":365},{"bransKodu":"721","bransAd":"ASANSÖR KAZA ÜÇÜNCÜ ŞAHISLARA KARŞI MALİ SORUMLULUK","ay":3,"vadeGun":365},{"bransKodu":"721","bransAd":"ASANSÖR KAZA ÜÇÜNCÜ ŞAHISLARA KARŞI MALİ SORUMLULUK","ay":4,"vadeGun":365},{"bransKodu":"721","bransAd":"ASANSÖR KAZA ÜÇÜNCÜ ŞAHISLARA KARŞI MALİ SORUMLULUK","ay":5,"vadeGun":365},{"bransKodu":"721","bransAd":"ASANSÖR KAZA ÜÇÜNCÜ ŞAHISLARA KARŞI MALİ SORUMLULUK","ay":6,"vadeGun":365},{"bransKodu":"721","bransAd":"ASANSÖR KAZA ÜÇÜNCÜ ŞAHISLARA KARŞI MALİ SORUMLULUK","ay":7,"vadeGun":365},{"bransKodu":"721","bransAd":"ASANSÖR KAZA ÜÇÜNCÜ ŞAHISLARA KARŞI MALİ SORUMLULUK","ay":8,"vadeGun":365},{"bransKodu":"721","bransAd":"ASANSÖR KAZA ÜÇÜNCÜ ŞAHISLARA KARŞI MALİ SORUMLULUK","ay":9,"vadeGun":365},{"bransKodu":"721","bransAd":"ASANSÖR KAZA ÜÇÜNCÜ ŞAHISLARA KARŞI MALİ SORUMLULUK","ay":10,"vadeGun":365},{"bransKodu":"721","bransAd":"ASANSÖR KAZA ÜÇÜNCÜ ŞAHISLARA KARŞI MALİ SORUMLULUK","ay":11,"vadeGun":365},{"bransKodu":"721","bransAd":"ASANSÖR KAZA ÜÇÜNCÜ ŞAHISLARA KARŞI MALİ SORUMLULUK","ay":12,"vadeGun":365},{"bransKodu":"722","bransAd":"ÇEVRE KİRLİLİĞİ MALİ SORUMLULUK","ay":1,"vadeGun":365},{"bransKodu":"722","bransAd":"ÇEVRE KİRLİLİĞİ MALİ SORUMLULUK","ay":2,"vadeGun":365},{"bransKodu":"722","bransAd":"ÇEVRE KİRLİLİĞİ MALİ SORUMLULUK","ay":3,"vadeGun":365},{"bransKodu":"722","bransAd":"ÇEVRE KİRLİLİĞİ MALİ SORUMLULUK","ay":4,"vadeGun":365},{"bransKodu":"722","bransAd":"ÇEVRE KİRLİLİĞİ MALİ SORUMLULUK","ay":5,"vadeGun":365},{"bransKodu":"722","bransAd":"ÇEVRE KİRLİLİĞİ MALİ SORUMLULUK","ay":6,"vadeGun":365},{"bransKodu":"722","bransAd":"ÇEVRE KİRLİLİĞİ MALİ SORUMLULUK","ay":7,"vadeGun":365},{"bransKodu":"722","bransAd":"ÇEVRE KİRLİLİĞİ MALİ SORUMLULUK","ay":8,"vadeGun":365},{"bransKodu":"722","bransAd":"ÇEVRE KİRLİLİĞİ MALİ SORUMLULUK","ay":9,"vadeGun":365},{"bransKodu":"722","bransAd":"ÇEVRE KİRLİLİĞİ MALİ SORUMLULUK","ay":10,"vadeGun":365},{"bransKodu":"722","bransAd":"ÇEVRE KİRLİLİĞİ MALİ SORUMLULUK","ay":11,"vadeGun":365},{"bransKodu":"722","bransAd":"ÇEVRE KİRLİLİĞİ MALİ SORUMLULUK","ay":12,"vadeGun":365},{"bransKodu":"723","bransAd":"CAM KIRILMASI","ay":1,"vadeGun":362.770787},{"bransKodu":"723","bransAd":"CAM KIRILMASI","ay":2,"vadeGun":364.584291},{"bransKodu":"723","bransAd":"CAM KIRILMASI","ay":3,"vadeGun":363.97681},{"bransKodu":"723","bransAd":"CAM KIRILMASI","ay":4,"vadeGun":364.168145},{"bransKodu":"723","bransAd":"CAM KIRILMASI","ay":5,"vadeGun":362.64005},{"bransKodu":"723","bransAd":"CAM KIRILMASI","ay":6,"vadeGun":363.588419},{"bransKodu":"723","bransAd":"CAM KIRILMASI","ay":7,"vadeGun":364.318497},{"bransKodu":"723","bransAd":"CAM KIRILMASI","ay":8,"vadeGun":363.758621},{"bransKodu":"723","bransAd":"CAM KIRILMASI","ay":9,"vadeGun":361.03455},{"bransKodu":"723","bransAd":"CAM KIRILMASI","ay":10,"vadeGun":360.477848},{"bransKodu":"723","bransAd":"CAM KIRILMASI","ay":11,"vadeGun":361.790899},{"bransKodu":"723","bransAd":"CAM KIRILMASI","ay":12,"vadeGun":361.194552},{"bransKodu":"724","bransAd":"HIRSIZLIK","ay":1,"vadeGun":360.975259},{"bransKodu":"724","bransAd":"HIRSIZLIK","ay":2,"vadeGun":364.211541},{"bransKodu":"724","bransAd":"HIRSIZLIK","ay":3,"vadeGun":363.397846},{"bransKodu":"724","bransAd":"HIRSIZLIK","ay":4,"vadeGun":363.360504},{"bransKodu":"724","bransAd":"HIRSIZLIK","ay":5,"vadeGun":362.778935},{"bransKodu":"724","bransAd":"HIRSIZLIK","ay":6,"vadeGun":363.231838},{"bransKodu":"724","bransAd":"HIRSIZLIK","ay":7,"vadeGun":363.871505},{"bransKodu":"724","bransAd":"HIRSIZLIK","ay":8,"vadeGun":362.971914},{"bransKodu":"724","bransAd":"HIRSIZLIK","ay":9,"vadeGun":358.602415},{"bransKodu":"724","bransAd":"HIRSIZLIK","ay":10,"vadeGun":358.025027},{"bransKodu":"724","bransAd":"HIRSIZLIK","ay":11,"vadeGun":358.709149},{"bransKodu":"724","bransAd":"HIRSIZLIK","ay":12,"vadeGun":360.670595},{"bransKodu":"725","bransAd":"TÜPGAZ ZORUNLU SORUMLULUK","ay":1,"vadeGun":365},{"bransKodu":"725","bransAd":"TÜPGAZ ZORUNLU SORUMLULUK","ay":2,"vadeGun":365},{"bransKodu":"725","bransAd":"TÜPGAZ ZORUNLU SORUMLULUK","ay":3,"vadeGun":365},{"bransKodu":"725","bransAd":"TÜPGAZ ZORUNLU SORUMLULUK","ay":4,"vadeGun":365},{"bransKodu":"725","bransAd":"TÜPGAZ ZORUNLU SORUMLULUK","ay":5,"vadeGun":365},{"bransKodu":"725","bransAd":"TÜPGAZ ZORUNLU SORUMLULUK","ay":6,"vadeGun":365},{"bransKodu":"725","bransAd":"TÜPGAZ ZORUNLU SORUMLULUK","ay":7,"vadeGun":365},{"bransKodu":"725","bransAd":"TÜPGAZ ZORUNLU SORUMLULUK","ay":8,"vadeGun":365},{"bransKodu":"725","bransAd":"TÜPGAZ ZORUNLU SORUMLULUK","ay":9,"vadeGun":365},{"bransKodu":"725","bransAd":"TÜPGAZ ZORUNLU SORUMLULUK","ay":10,"vadeGun":365},{"bransKodu":"725","bransAd":"TÜPGAZ ZORUNLU SORUMLULUK","ay":11,"vadeGun":365},{"bransKodu":"725","bransAd":"TÜPGAZ ZORUNLU SORUMLULUK","ay":12,"vadeGun":365},{"bransKodu":"726","bransAd":"TEHLİKE MADDELER ZORUNLU SORUMLULUK","ay":1,"vadeGun":361.233783},{"bransKodu":"726","bransAd":"TEHLİKE MADDELER ZORUNLU SORUMLULUK","ay":2,"vadeGun":362.729926},{"bransKodu":"726","bransAd":"TEHLİKE MADDELER ZORUNLU SORUMLULUK","ay":3,"vadeGun":348.022296},{"bransKodu":"726","bransAd":"TEHLİKE MADDELER ZORUNLU SORUMLULUK","ay":4,"vadeGun":361.0625},{"bransKodu":"726","bransAd":"TEHLİKE MADDELER ZORUNLU SORUMLULUK","ay":5,"vadeGun":360.037037},{"bransKodu":"726","bransAd":"TEHLİKE MADDELER ZORUNLU SORUMLULUK","ay":6,"vadeGun":360.727097},{"bransKodu":"726","bransAd":"TEHLİKE MADDELER ZORUNLU SORUMLULUK","ay":7,"vadeGun":361.626882},{"bransKodu":"726","bransAd":"TEHLİKE MADDELER ZORUNLU SORUMLULUK","ay":8,"vadeGun":365.333333},{"bransKodu":"726","bransAd":"TEHLİKE MADDELER ZORUNLU SORUMLULUK","ay":9,"vadeGun":358.453333},{"bransKodu":"726","bransAd":"TEHLİKE MADDELER ZORUNLU SORUMLULUK","ay":10,"vadeGun":357.763158},{"bransKodu":"726","bransAd":"TEHLİKE MADDELER ZORUNLU SORUMLULUK","ay":11,"vadeGun":349.961905},{"bransKodu":"726","bransAd":"TEHLİKE MADDELER ZORUNLU SORUMLULUK","ay":12,"vadeGun":365.252351},{"bransKodu":"727","bransAd":"UÇAK TEKNE","ay":1,"vadeGun":365},{"bransKodu":"727","bransAd":"UÇAK TEKNE","ay":2,"vadeGun":365},{"bransKodu":"727","bransAd":"UÇAK TEKNE","ay":3,"vadeGun":365},{"bransKodu":"727","bransAd":"UÇAK TEKNE","ay":4,"vadeGun":365},{"bransKodu":"727","bransAd":"UÇAK TEKNE","ay":5,"vadeGun":365},{"bransKodu":"727","bransAd":"UÇAK TEKNE","ay":6,"vadeGun":365},{"bransKodu":"727","bransAd":"UÇAK TEKNE","ay":7,"vadeGun":365},{"bransKodu":"727","bransAd":"UÇAK TEKNE","ay":8,"vadeGun":365},{"bransKodu":"727","bransAd":"UÇAK TEKNE","ay":9,"vadeGun":365},{"bransKodu":"727","bransAd":"UÇAK TEKNE","ay":10,"vadeGun":365},{"bransKodu":"727","bransAd":"UÇAK TEKNE","ay":11,"vadeGun":365},{"bransKodu":"727","bransAd":"UÇAK TEKNE","ay":12,"vadeGun":365},{"bransKodu":"728","bransAd":"UÇAK MALİ MESULİYET","ay":1,"vadeGun":365},{"bransKodu":"728","bransAd":"UÇAK MALİ MESULİYET","ay":2,"vadeGun":365},{"bransKodu":"728","bransAd":"UÇAK MALİ MESULİYET","ay":3,"vadeGun":365},{"bransKodu":"728","bransAd":"UÇAK MALİ MESULİYET","ay":4,"vadeGun":365},{"bransKodu":"728","bransAd":"UÇAK MALİ MESULİYET","ay":5,"vadeGun":365},{"bransKodu":"728","bransAd":"UÇAK MALİ MESULİYET","ay":6,"vadeGun":365},{"bransKodu":"728","bransAd":"UÇAK MALİ MESULİYET","ay":7,"vadeGun":365},{"bransKodu":"728","bransAd":"UÇAK MALİ MESULİYET","ay":8,"vadeGun":365},{"bransKodu":"728","bransAd":"UÇAK MALİ MESULİYET","ay":9,"vadeGun":365},{"bransKodu":"728","bransAd":"UÇAK MALİ MESULİYET","ay":10,"vadeGun":365},{"bransKodu":"728","bransAd":"UÇAK MALİ MESULİYET","ay":11,"vadeGun":365},{"bransKodu":"728","bransAd":"UÇAK MALİ MESULİYET","ay":12,"vadeGun":365},{"bransKodu":"729","bransAd":"UÇAK YOLCU KAZA","ay":1,"vadeGun":365},{"bransKodu":"729","bransAd":"UÇAK YOLCU KAZA","ay":2,"vadeGun":365},{"bransKodu":"729","bransAd":"UÇAK YOLCU KAZA","ay":3,"vadeGun":365},{"bransKodu":"729","bransAd":"UÇAK YOLCU KAZA","ay":4,"vadeGun":365},{"bransKodu":"729","bransAd":"UÇAK YOLCU KAZA","ay":5,"vadeGun":365},{"bransKodu":"729","bransAd":"UÇAK YOLCU KAZA","ay":6,"vadeGun":365},{"bransKodu":"729","bransAd":"UÇAK YOLCU KAZA","ay":7,"vadeGun":365},{"bransKodu":"729","bransAd":"UÇAK YOLCU KAZA","ay":8,"vadeGun":365},{"bransKodu":"729","bransAd":"UÇAK YOLCU KAZA","ay":9,"vadeGun":365},{"bransKodu":"729","bransAd":"UÇAK YOLCU KAZA","ay":10,"vadeGun":365},{"bransKodu":"729","bransAd":"UÇAK YOLCU KAZA","ay":11,"vadeGun":365},{"bransKodu":"729","bransAd":"UÇAK YOLCU KAZA","ay":12,"vadeGun":365},{"bransKodu":"730","bransAd":"TIBBİ KÖTÜ UYGULAMA","ay":1,"vadeGun":365.333333},{"bransKodu":"730","bransAd":"TIBBİ KÖTÜ UYGULAMA","ay":2,"vadeGun":365.403914},{"bransKodu":"730","bransAd":"TIBBİ KÖTÜ UYGULAMA","ay":3,"vadeGun":365.333333},{"bransKodu":"730","bransAd":"TIBBİ KÖTÜ UYGULAMA","ay":4,"vadeGun":365.333333},{"bransKodu":"730","bransAd":"TIBBİ KÖTÜ UYGULAMA","ay":5,"vadeGun":365.333333},{"bransKodu":"730","bransAd":"TIBBİ KÖTÜ UYGULAMA","ay":6,"vadeGun":365.333333},{"bransKodu":"730","bransAd":"TIBBİ KÖTÜ UYGULAMA","ay":7,"vadeGun":365.333333},{"bransKodu":"730","bransAd":"TIBBİ KÖTÜ UYGULAMA","ay":8,"vadeGun":365.333333},{"bransKodu":"730","bransAd":"TIBBİ KÖTÜ UYGULAMA","ay":9,"vadeGun":365.333333},{"bransKodu":"730","bransAd":"TIBBİ KÖTÜ UYGULAMA","ay":10,"vadeGun":365.333333},{"bransKodu":"730","bransAd":"TIBBİ KÖTÜ UYGULAMA","ay":11,"vadeGun":365.333333},{"bransKodu":"730","bransAd":"TIBBİ KÖTÜ UYGULAMA","ay":12,"vadeGun":365.333333},{"bransKodu":"731","bransAd":"ÖZEL GÜVENLİK MALİ SORUMLULUK","ay":1,"vadeGun":365.333333},{"bransKodu":"731","bransAd":"ÖZEL GÜVENLİK MALİ SORUMLULUK","ay":2,"vadeGun":365.333333},{"bransKodu":"731","bransAd":"ÖZEL GÜVENLİK MALİ SORUMLULUK","ay":3,"vadeGun":365.333333},{"bransKodu":"731","bransAd":"ÖZEL GÜVENLİK MALİ SORUMLULUK","ay":4,"vadeGun":365.333333},{"bransKodu":"731","bransAd":"ÖZEL GÜVENLİK MALİ SORUMLULUK","ay":5,"vadeGun":365.333333},{"bransKodu":"731","bransAd":"ÖZEL GÜVENLİK MALİ SORUMLULUK","ay":6,"vadeGun":365.333333},{"bransKodu":"731","bransAd":"ÖZEL GÜVENLİK MALİ SORUMLULUK","ay":7,"vadeGun":365.333333},{"bransKodu":"731","bransAd":"ÖZEL GÜVENLİK MALİ SORUMLULUK","ay":8,"vadeGun":365.333333},{"bransKodu":"731","bransAd":"ÖZEL GÜVENLİK MALİ SORUMLULUK","ay":9,"vadeGun":365.333333},{"bransKodu":"731","bransAd":"ÖZEL GÜVENLİK MALİ SORUMLULUK","ay":10,"vadeGun":365.333333},{"bransKodu":"731","bransAd":"ÖZEL GÜVENLİK MALİ SORUMLULUK","ay":11,"vadeGun":365.333333},{"bransKodu":"731","bransAd":"ÖZEL GÜVENLİK MALİ SORUMLULUK","ay":12,"vadeGun":365.333333},{"bransKodu":"732","bransAd":"ZORUNLU SERTİFİKA MALİ SORUMLULUK","ay":1,"vadeGun":365},{"bransKodu":"732","bransAd":"ZORUNLU SERTİFİKA MALİ SORUMLULUK","ay":2,"vadeGun":365},{"bransKodu":"732","bransAd":"ZORUNLU SERTİFİKA MALİ SORUMLULUK","ay":3,"vadeGun":365},{"bransKodu":"732","bransAd":"ZORUNLU SERTİFİKA MALİ SORUMLULUK","ay":4,"vadeGun":365},{"bransKodu":"732","bransAd":"ZORUNLU SERTİFİKA MALİ SORUMLULUK","ay":5,"vadeGun":365},{"bransKodu":"732","bransAd":"ZORUNLU SERTİFİKA MALİ SORUMLULUK","ay":6,"vadeGun":365},{"bransKodu":"732","bransAd":"ZORUNLU SERTİFİKA MALİ SORUMLULUK","ay":7,"vadeGun":365},{"bransKodu":"732","bransAd":"ZORUNLU SERTİFİKA MALİ SORUMLULUK","ay":8,"vadeGun":365},{"bransKodu":"732","bransAd":"ZORUNLU SERTİFİKA MALİ SORUMLULUK","ay":9,"vadeGun":365},{"bransKodu":"732","bransAd":"ZORUNLU SERTİFİKA MALİ SORUMLULUK","ay":10,"vadeGun":365},{"bransKodu":"732","bransAd":"ZORUNLU SERTİFİKA MALİ SORUMLULUK","ay":11,"vadeGun":365},{"bransKodu":"732","bransAd":"ZORUNLU SERTİFİKA MALİ SORUMLULUK","ay":12,"vadeGun":365},{"bransKodu":"733","bransAd":"MESLEKİ SORUMLULUK","ay":1,"vadeGun":330.803922},{"bransKodu":"733","bransAd":"MESLEKİ SORUMLULUK","ay":2,"vadeGun":358.294872},{"bransKodu":"733","bransAd":"MESLEKİ SORUMLULUK","ay":3,"vadeGun":327.179487},{"bransKodu":"733","bransAd":"MESLEKİ SORUMLULUK","ay":4,"vadeGun":290.74188},{"bransKodu":"733","bransAd":"MESLEKİ SORUMLULUK","ay":5,"vadeGun":343.458333},{"bransKodu":"733","bransAd":"MESLEKİ SORUMLULUK","ay":6,"vadeGun":341.573975},{"bransKodu":"733","bransAd":"MESLEKİ SORUMLULUK","ay":7,"vadeGun":354.605994},{"bransKodu":"733","bransAd":"MESLEKİ SORUMLULUK","ay":8,"vadeGun":352.562842},{"bransKodu":"733","bransAd":"MESLEKİ SORUMLULUK","ay":9,"vadeGun":360.818627},{"bransKodu":"733","bransAd":"MESLEKİ SORUMLULUK","ay":10,"vadeGun":293.07619},{"bransKodu":"733","bransAd":"MESLEKİ SORUMLULUK","ay":11,"vadeGun":345.111111},{"bransKodu":"733","bransAd":"MESLEKİ SORUMLULUK","ay":12,"vadeGun":332.242424},{"bransKodu":"734","bransAd":"KIYI TESİSLERİ DENİZ KİRLİLİĞİ ZORUNLU MALİ SORUMLULUK","ay":1,"vadeGun":365.5},{"bransKodu":"734","bransAd":"KIYI TESİSLERİ DENİZ KİRLİLİĞİ ZORUNLU MALİ SORUMLULUK","ay":2,"vadeGun":365},{"bransKodu":"734","bransAd":"KIYI TESİSLERİ DENİZ KİRLİLİĞİ ZORUNLU MALİ SORUMLULUK","ay":3,"vadeGun":366},{"bransKodu":"734","bransAd":"KIYI TESİSLERİ DENİZ KİRLİLİĞİ ZORUNLU MALİ SORUMLULUK","ay":4,"vadeGun":365.333333},{"bransKodu":"734","bransAd":"KIYI TESİSLERİ DENİZ KİRLİLİĞİ ZORUNLU MALİ SORUMLULUK","ay":5,"vadeGun":365.333333},{"bransKodu":"734","bransAd":"KIYI TESİSLERİ DENİZ KİRLİLİĞİ ZORUNLU MALİ SORUMLULUK","ay":6,"vadeGun":365},{"bransKodu":"734","bransAd":"KIYI TESİSLERİ DENİZ KİRLİLİĞİ ZORUNLU MALİ SORUMLULUK","ay":7,"vadeGun":365.333333},{"bransKodu":"734","bransAd":"KIYI TESİSLERİ DENİZ KİRLİLİĞİ ZORUNLU MALİ SORUMLULUK","ay":8,"vadeGun":365},{"bransKodu":"734","bransAd":"KIYI TESİSLERİ DENİZ KİRLİLİĞİ ZORUNLU MALİ SORUMLULUK","ay":9,"vadeGun":365.333333},{"bransKodu":"734","bransAd":"KIYI TESİSLERİ DENİZ KİRLİLİĞİ ZORUNLU MALİ SORUMLULUK","ay":10,"vadeGun":365},{"bransKodu":"734","bransAd":"KIYI TESİSLERİ DENİZ KİRLİLİĞİ ZORUNLU MALİ SORUMLULUK","ay":11,"vadeGun":366},{"bransKodu":"734","bransAd":"KIYI TESİSLERİ DENİZ KİRLİLİĞİ ZORUNLU MALİ SORUMLULUK","ay":12,"vadeGun":365},{"bransKodu":"735","bransAd":"TEKNE SORUMLULUK","ay":1,"vadeGun":365},{"bransKodu":"735","bransAd":"TEKNE SORUMLULUK","ay":2,"vadeGun":365},{"bransKodu":"735","bransAd":"TEKNE SORUMLULUK","ay":3,"vadeGun":365},{"bransKodu":"735","bransAd":"TEKNE SORUMLULUK","ay":4,"vadeGun":365},{"bransKodu":"735","bransAd":"TEKNE SORUMLULUK","ay":5,"vadeGun":365},{"bransKodu":"735","bransAd":"TEKNE SORUMLULUK","ay":6,"vadeGun":365},{"bransKodu":"735","bransAd":"TEKNE SORUMLULUK","ay":7,"vadeGun":365},{"bransKodu":"735","bransAd":"TEKNE SORUMLULUK","ay":8,"vadeGun":365},{"bransKodu":"735","bransAd":"TEKNE SORUMLULUK","ay":9,"vadeGun":365},{"bransKodu":"735","bransAd":"TEKNE SORUMLULUK","ay":10,"vadeGun":365},{"bransKodu":"735","bransAd":"TEKNE SORUMLULUK","ay":11,"vadeGun":365},{"bransKodu":"735","bransAd":"TEKNE SORUMLULUK","ay":12,"vadeGun":365},{"bransKodu":"736","bransAd":"EMNİYETİ SUİSTİMAL","ay":1,"vadeGun":355.513233},{"bransKodu":"736","bransAd":"EMNİYETİ SUİSTİMAL","ay":2,"vadeGun":363.240583},{"bransKodu":"736","bransAd":"EMNİYETİ SUİSTİMAL","ay":3,"vadeGun":350.904326},{"bransKodu":"736","bransAd":"EMNİYETİ SUİSTİMAL","ay":4,"vadeGun":342.651752},{"bransKodu":"736","bransAd":"EMNİYETİ SUİSTİMAL","ay":5,"vadeGun":337.106523},{"bransKodu":"736","bransAd":"EMNİYETİ SUİSTİMAL","ay":6,"vadeGun":337.368102},{"bransKodu":"736","bransAd":"EMNİYETİ SUİSTİMAL","ay":7,"vadeGun":344.507149},{"bransKodu":"736","bransAd":"EMNİYETİ SUİSTİMAL","ay":8,"vadeGun":343.289395},{"bransKodu":"736","bransAd":"EMNİYETİ SUİSTİMAL","ay":9,"vadeGun":324.189451},{"bransKodu":"736","bransAd":"EMNİYETİ SUİSTİMAL","ay":10,"vadeGun":320.870481},{"bransKodu":"736","bransAd":"EMNİYETİ SUİSTİMAL","ay":11,"vadeGun":324.692656},{"bransKodu":"736","bransAd":"EMNİYETİ SUİSTİMAL","ay":12,"vadeGun":316.355777},{"bransKodu":"737","bransAd":"MOTORLU KARA TAŞITLARI DIŞINDAKİ KARA TAŞITLARI","ay":1,"vadeGun":365},{"bransKodu":"737","bransAd":"MOTORLU KARA TAŞITLARI DIŞINDAKİ KARA TAŞITLARI","ay":2,"vadeGun":365},{"bransKodu":"737","bransAd":"MOTORLU KARA TAŞITLARI DIŞINDAKİ KARA TAŞITLARI","ay":3,"vadeGun":365},{"bransKodu":"737","bransAd":"MOTORLU KARA TAŞITLARI DIŞINDAKİ KARA TAŞITLARI","ay":4,"vadeGun":365},{"bransKodu":"737","bransAd":"MOTORLU KARA TAŞITLARI DIŞINDAKİ KARA TAŞITLARI","ay":5,"vadeGun":365},{"bransKodu":"737","bransAd":"MOTORLU KARA TAŞITLARI DIŞINDAKİ KARA TAŞITLARI","ay":6,"vadeGun":365},{"bransKodu":"737","bransAd":"MOTORLU KARA TAŞITLARI DIŞINDAKİ KARA TAŞITLARI","ay":7,"vadeGun":365},{"bransKodu":"737","bransAd":"MOTORLU KARA TAŞITLARI DIŞINDAKİ KARA TAŞITLARI","ay":8,"vadeGun":365},{"bransKodu":"737","bransAd":"MOTORLU KARA TAŞITLARI DIŞINDAKİ KARA TAŞITLARI","ay":9,"vadeGun":365},{"bransKodu":"737","bransAd":"MOTORLU KARA TAŞITLARI DIŞINDAKİ KARA TAŞITLARI","ay":10,"vadeGun":365},{"bransKodu":"737","bransAd":"MOTORLU KARA TAŞITLARI DIŞINDAKİ KARA TAŞITLARI","ay":11,"vadeGun":365},{"bransKodu":"737","bransAd":"MOTORLU KARA TAŞITLARI DIŞINDAKİ KARA TAŞITLARI","ay":12,"vadeGun":365},{"bransKodu":"738","bransAd":"NEHİR ARAÇLARI","ay":1,"vadeGun":365},{"bransKodu":"738","bransAd":"NEHİR ARAÇLARI","ay":2,"vadeGun":365},{"bransKodu":"738","bransAd":"NEHİR ARAÇLARI","ay":3,"vadeGun":365},{"bransKodu":"738","bransAd":"NEHİR ARAÇLARI","ay":4,"vadeGun":365},{"bransKodu":"738","bransAd":"NEHİR ARAÇLARI","ay":5,"vadeGun":365},{"bransKodu":"738","bransAd":"NEHİR ARAÇLARI","ay":6,"vadeGun":365},{"bransKodu":"738","bransAd":"NEHİR ARAÇLARI","ay":7,"vadeGun":365},{"bransKodu":"738","bransAd":"NEHİR ARAÇLARI","ay":8,"vadeGun":365},{"bransKodu":"738","bransAd":"NEHİR ARAÇLARI","ay":9,"vadeGun":365},{"bransKodu":"738","bransAd":"NEHİR ARAÇLARI","ay":10,"vadeGun":365},{"bransKodu":"738","bransAd":"NEHİR ARAÇLARI","ay":11,"vadeGun":365},{"bransKodu":"738","bransAd":"NEHİR ARAÇLARI","ay":12,"vadeGun":365},{"bransKodu":"739","bransAd":"GÖL ARAÇLARI","ay":1,"vadeGun":365},{"bransKodu":"739","bransAd":"GÖL ARAÇLARI","ay":2,"vadeGun":365},{"bransKodu":"739","bransAd":"GÖL ARAÇLARI","ay":3,"vadeGun":365},{"bransKodu":"739","bransAd":"GÖL ARAÇLARI","ay":4,"vadeGun":365},{"bransKodu":"739","bransAd":"GÖL ARAÇLARI","ay":5,"vadeGun":365},{"bransKodu":"739","bransAd":"GÖL ARAÇLARI","ay":6,"vadeGun":365},{"bransKodu":"739","bransAd":"GÖL ARAÇLARI","ay":7,"vadeGun":365},{"bransKodu":"739","bransAd":"GÖL ARAÇLARI","ay":8,"vadeGun":365},{"bransKodu":"739","bransAd":"GÖL ARAÇLARI","ay":9,"vadeGun":365},{"bransKodu":"739","bransAd":"GÖL ARAÇLARI","ay":10,"vadeGun":365},{"bransKodu":"739","bransAd":"GÖL ARAÇLARI","ay":11,"vadeGun":365},{"bransKodu":"739","bransAd":"GÖL ARAÇLARI","ay":12,"vadeGun":365},{"bransKodu":"740","bransAd":"İHTİYARİ DEPREM","ay":1,"vadeGun":363.703214},{"bransKodu":"740","bransAd":"İHTİYARİ DEPREM","ay":2,"vadeGun":364.25061},{"bransKodu":"740","bransAd":"İHTİYARİ DEPREM","ay":3,"vadeGun":363.301861},{"bransKodu":"740","bransAd":"İHTİYARİ DEPREM","ay":4,"vadeGun":363.601068},{"bransKodu":"740","bransAd":"İHTİYARİ DEPREM","ay":5,"vadeGun":361.407843},{"bransKodu":"740","bransAd":"İHTİYARİ DEPREM","ay":6,"vadeGun":362.426261},{"bransKodu":"740","bransAd":"İHTİYARİ DEPREM","ay":7,"vadeGun":364.333081},{"bransKodu":"740","bransAd":"İHTİYARİ DEPREM","ay":8,"vadeGun":363.301772},{"bransKodu":"740","bransAd":"İHTİYARİ DEPREM","ay":9,"vadeGun":360.985546},{"bransKodu":"740","bransAd":"İHTİYARİ DEPREM","ay":10,"vadeGun":360.910738},{"bransKodu":"740","bransAd":"İHTİYARİ DEPREM","ay":11,"vadeGun":362.203018},{"bransKodu":"740","bransAd":"İHTİYARİ DEPREM","ay":12,"vadeGun":362.325304},{"bransKodu":"741","bransAd":"SEL","ay":1,"vadeGun":361.176881},{"bransKodu":"741","bransAd":"SEL","ay":2,"vadeGun":361.926102},{"bransKodu":"741","bransAd":"SEL","ay":3,"vadeGun":351.540188},{"bransKodu":"741","bransAd":"SEL","ay":4,"vadeGun":351.894007},{"bransKodu":"741","bransAd":"SEL","ay":5,"vadeGun":342.301803},{"bransKodu":"741","bransAd":"SEL","ay":6,"vadeGun":344.631185},{"bransKodu":"741","bransAd":"SEL","ay":7,"vadeGun":355.346633},{"bransKodu":"741","bransAd":"SEL","ay":8,"vadeGun":350.261504},{"bransKodu":"741","bransAd":"SEL","ay":9,"vadeGun":344.071117},{"bransKodu":"741","bransAd":"SEL","ay":10,"vadeGun":344.173023},{"bransKodu":"741","bransAd":"SEL","ay":11,"vadeGun":344.680536},{"bransKodu":"741","bransAd":"SEL","ay":12,"vadeGun":350.625444},{"bransKodu":"742","bransAd":"DEPREM VE SEL DIŞINDAKİ DOĞAL AFETLER","ay":1,"vadeGun":361.188647},{"bransKodu":"742","bransAd":"DEPREM VE SEL DIŞINDAKİ DOĞAL AFETLER","ay":2,"vadeGun":361.834794},{"bransKodu":"742","bransAd":"DEPREM VE SEL DIŞINDAKİ DOĞAL AFETLER","ay":3,"vadeGun":351.49929},{"bransKodu":"742","bransAd":"DEPREM VE SEL DIŞINDAKİ DOĞAL AFETLER","ay":4,"vadeGun":351.829643},{"bransKodu":"742","bransAd":"DEPREM VE SEL DIŞINDAKİ DOĞAL AFETLER","ay":5,"vadeGun":342.604926},{"bransKodu":"742","bransAd":"DEPREM VE SEL DIŞINDAKİ DOĞAL AFETLER","ay":6,"vadeGun":344.530925},{"bransKodu":"742","bransAd":"DEPREM VE SEL DIŞINDAKİ DOĞAL AFETLER","ay":7,"vadeGun":355.316801},{"bransKodu":"742","bransAd":"DEPREM VE SEL DIŞINDAKİ DOĞAL AFETLER","ay":8,"vadeGun":350.144002},{"bransKodu":"742","bransAd":"DEPREM VE SEL DIŞINDAKİ DOĞAL AFETLER","ay":9,"vadeGun":344.513496},{"bransKodu":"742","bransAd":"DEPREM VE SEL DIŞINDAKİ DOĞAL AFETLER","ay":10,"vadeGun":344.011779},{"bransKodu":"742","bransAd":"DEPREM VE SEL DIŞINDAKİ DOĞAL AFETLER","ay":11,"vadeGun":344.459289},{"bransKodu":"742","bransAd":"DEPREM VE SEL DIŞINDAKİ DOĞAL AFETLER","ay":12,"vadeGun":350.547703},{"bransKodu":"743","bransAd":"NÜKLEER ENERJİ","ay":1,"vadeGun":365},{"bransKodu":"743","bransAd":"NÜKLEER ENERJİ","ay":2,"vadeGun":365},{"bransKodu":"743","bransAd":"NÜKLEER ENERJİ","ay":3,"vadeGun":365},{"bransKodu":"743","bransAd":"NÜKLEER ENERJİ","ay":4,"vadeGun":365},{"bransKodu":"743","bransAd":"NÜKLEER ENERJİ","ay":5,"vadeGun":365},{"bransKodu":"743","bransAd":"NÜKLEER ENERJİ","ay":6,"vadeGun":365},{"bransKodu":"743","bransAd":"NÜKLEER ENERJİ","ay":7,"vadeGun":365},{"bransKodu":"743","bransAd":"NÜKLEER ENERJİ","ay":8,"vadeGun":365},{"bransKodu":"743","bransAd":"NÜKLEER ENERJİ","ay":9,"vadeGun":365},{"bransKodu":"743","bransAd":"NÜKLEER ENERJİ","ay":10,"vadeGun":365},{"bransKodu":"743","bransAd":"NÜKLEER ENERJİ","ay":11,"vadeGun":365},{"bransKodu":"743","bransAd":"NÜKLEER ENERJİ","ay":12,"vadeGun":365},{"bransKodu":"744","bransAd":"TOPRAK KAYMASI","ay":1,"vadeGun":366},{"bransKodu":"744","bransAd":"TOPRAK KAYMASI","ay":2,"vadeGun":365},{"bransKodu":"744","bransAd":"TOPRAK KAYMASI","ay":3,"vadeGun":365},{"bransKodu":"744","bransAd":"TOPRAK KAYMASI","ay":4,"vadeGun":365},{"bransKodu":"744","bransAd":"TOPRAK KAYMASI","ay":5,"vadeGun":365},{"bransKodu":"744","bransAd":"TOPRAK KAYMASI","ay":6,"vadeGun":365},{"bransKodu":"744","bransAd":"TOPRAK KAYMASI","ay":7,"vadeGun":365},{"bransKodu":"744","bransAd":"TOPRAK KAYMASI","ay":8,"vadeGun":365},{"bransKodu":"744","bransAd":"TOPRAK KAYMASI","ay":9,"vadeGun":365},{"bransKodu":"744","bransAd":"TOPRAK KAYMASI","ay":10,"vadeGun":365},{"bransKodu":"744","bransAd":"TOPRAK KAYMASI","ay":11,"vadeGun":365},{"bransKodu":"744","bransAd":"TOPRAK KAYMASI","ay":12,"vadeGun":365},{"bransKodu":"745","bransAd":"TAKSİTLİ KREDİ","ay":1,"vadeGun":365},{"bransKodu":"745","bransAd":"TAKSİTLİ KREDİ","ay":2,"vadeGun":365},{"bransKodu":"745","bransAd":"TAKSİTLİ KREDİ","ay":3,"vadeGun":365},{"bransKodu":"745","bransAd":"TAKSİTLİ KREDİ","ay":4,"vadeGun":365},{"bransKodu":"745","bransAd":"TAKSİTLİ KREDİ","ay":5,"vadeGun":365},{"bransKodu":"745","bransAd":"TAKSİTLİ KREDİ","ay":6,"vadeGun":365},{"bransKodu":"745","bransAd":"TAKSİTLİ KREDİ","ay":7,"vadeGun":365},{"bransKodu":"745","bransAd":"TAKSİTLİ KREDİ","ay":8,"vadeGun":365},{"bransKodu":"745","bransAd":"TAKSİTLİ KREDİ","ay":9,"vadeGun":365},{"bransKodu":"745","bransAd":"TAKSİTLİ KREDİ","ay":10,"vadeGun":365},{"bransKodu":"745","bransAd":"TAKSİTLİ KREDİ","ay":11,"vadeGun":365},{"bransKodu":"745","bransAd":"TAKSİTLİ KREDİ","ay":12,"vadeGun":365},{"bransKodu":"746","bransAd":"UZUN VADELİ KONUT KREDİSİ","ay":1,"vadeGun":365},{"bransKodu":"746","bransAd":"UZUN VADELİ KONUT KREDİSİ","ay":2,"vadeGun":365},{"bransKodu":"746","bransAd":"UZUN VADELİ KONUT KREDİSİ","ay":3,"vadeGun":365},{"bransKodu":"746","bransAd":"UZUN VADELİ KONUT KREDİSİ","ay":4,"vadeGun":365},{"bransKodu":"746","bransAd":"UZUN VADELİ KONUT KREDİSİ","ay":5,"vadeGun":365},{"bransKodu":"746","bransAd":"UZUN VADELİ KONUT KREDİSİ","ay":6,"vadeGun":365},{"bransKodu":"746","bransAd":"UZUN VADELİ KONUT KREDİSİ","ay":7,"vadeGun":365},{"bransKodu":"746","bransAd":"UZUN VADELİ KONUT KREDİSİ","ay":8,"vadeGun":365},{"bransKodu":"746","bransAd":"UZUN VADELİ KONUT KREDİSİ","ay":9,"vadeGun":365},{"bransKodu":"746","bransAd":"UZUN VADELİ KONUT KREDİSİ","ay":10,"vadeGun":365},{"bransKodu":"746","bransAd":"UZUN VADELİ KONUT KREDİSİ","ay":11,"vadeGun":365},{"bransKodu":"746","bransAd":"UZUN VADELİ KONUT KREDİSİ","ay":12,"vadeGun":365},{"bransKodu":"747","bransAd":"TARIM KREDİSİ","ay":1,"vadeGun":365},{"bransKodu":"747","bransAd":"TARIM KREDİSİ","ay":2,"vadeGun":365},{"bransKodu":"747","bransAd":"TARIM KREDİSİ","ay":3,"vadeGun":365},{"bransKodu":"747","bransAd":"TARIM KREDİSİ","ay":4,"vadeGun":365},{"bransKodu":"747","bransAd":"TARIM KREDİSİ","ay":5,"vadeGun":365},{"bransKodu":"747","bransAd":"TARIM KREDİSİ","ay":6,"vadeGun":365},{"bransKodu":"747","bransAd":"TARIM KREDİSİ","ay":7,"vadeGun":365},{"bransKodu":"747","bransAd":"TARIM KREDİSİ","ay":8,"vadeGun":365},{"bransKodu":"747","bransAd":"TARIM KREDİSİ","ay":9,"vadeGun":365},{"bransKodu":"747","bransAd":"TARIM KREDİSİ","ay":10,"vadeGun":365},{"bransKodu":"747","bransAd":"TARIM KREDİSİ","ay":11,"vadeGun":365},{"bransKodu":"747","bransAd":"TARIM KREDİSİ","ay":12,"vadeGun":365},{"bransKodu":"748","bransAd":"İSTİHDAM","ay":1,"vadeGun":365},{"bransKodu":"748","bransAd":"İSTİHDAM","ay":2,"vadeGun":365},{"bransKodu":"748","bransAd":"İSTİHDAM","ay":3,"vadeGun":365},{"bransKodu":"748","bransAd":"İSTİHDAM","ay":4,"vadeGun":365},{"bransKodu":"748","bransAd":"İSTİHDAM","ay":5,"vadeGun":365},{"bransKodu":"748","bransAd":"İSTİHDAM","ay":6,"vadeGun":365},{"bransKodu":"748","bransAd":"İSTİHDAM","ay":7,"vadeGun":365},{"bransKodu":"748","bransAd":"İSTİHDAM","ay":8,"vadeGun":365},{"bransKodu":"748","bransAd":"İSTİHDAM","ay":9,"vadeGun":365},{"bransKodu":"748","bransAd":"İSTİHDAM","ay":10,"vadeGun":365},{"bransKodu":"748","bransAd":"İSTİHDAM","ay":11,"vadeGun":365},{"bransKodu":"748","bransAd":"İSTİHDAM","ay":12,"vadeGun":365},{"bransKodu":"749","bransAd":"GELİR YETERSİZLİĞİ","ay":1,"vadeGun":365},{"bransKodu":"749","bransAd":"GELİR YETERSİZLİĞİ","ay":2,"vadeGun":365},{"bransKodu":"749","bransAd":"GELİR YETERSİZLİĞİ","ay":3,"vadeGun":365},{"bransKodu":"749","bransAd":"GELİR YETERSİZLİĞİ","ay":4,"vadeGun":365},{"bransKodu":"749","bransAd":"GELİR YETERSİZLİĞİ","ay":5,"vadeGun":365},{"bransKodu":"749","bransAd":"GELİR YETERSİZLİĞİ","ay":6,"vadeGun":365},{"bransKodu":"749","bransAd":"GELİR YETERSİZLİĞİ","ay":7,"vadeGun":365},{"bransKodu":"749","bransAd":"GELİR YETERSİZLİĞİ","ay":8,"vadeGun":365},{"bransKodu":"749","bransAd":"GELİR YETERSİZLİĞİ","ay":9,"vadeGun":365},{"bransKodu":"749","bransAd":"GELİR YETERSİZLİĞİ","ay":10,"vadeGun":365},{"bransKodu":"749","bransAd":"GELİR YETERSİZLİĞİ","ay":11,"vadeGun":365},{"bransKodu":"749","bransAd":"GELİR YETERSİZLİĞİ","ay":12,"vadeGun":365},{"bransKodu":"750","bransAd":"FERDİ KAZA","ay":1,"vadeGun":359.976912},{"bransKodu":"750","bransAd":"FERDİ KAZA","ay":2,"vadeGun":364.276253},{"bransKodu":"750","bransAd":"FERDİ KAZA","ay":3,"vadeGun":363.360576},{"bransKodu":"750","bransAd":"FERDİ KAZA","ay":4,"vadeGun":363.061635},{"bransKodu":"750","bransAd":"FERDİ KAZA","ay":5,"vadeGun":363.160674},{"bransKodu":"750","bransAd":"FERDİ KAZA","ay":6,"vadeGun":362.678506},{"bransKodu":"750","bransAd":"FERDİ KAZA","ay":7,"vadeGun":363.748411},{"bransKodu":"750","bransAd":"FERDİ KAZA","ay":8,"vadeGun":362.748521},{"bransKodu":"750","bransAd":"FERDİ KAZA","ay":9,"vadeGun":360.949341},{"bransKodu":"750","bransAd":"FERDİ KAZA","ay":10,"vadeGun":361.275454},{"bransKodu":"750","bransAd":"FERDİ KAZA","ay":11,"vadeGun":359.578104},{"bransKodu":"750","bransAd":"FERDİ KAZA","ay":12,"vadeGun":360.653096},{"bransKodu":"751","bransAd":"UZUN SÜRELİ FERDİ KAZA","ay":1,"vadeGun":365},{"bransKodu":"751","bransAd":"UZUN SÜRELİ FERDİ KAZA","ay":2,"vadeGun":365},{"bransKodu":"751","bransAd":"UZUN SÜRELİ FERDİ KAZA","ay":3,"vadeGun":365},{"bransKodu":"751","bransAd":"UZUN SÜRELİ FERDİ KAZA","ay":4,"vadeGun":365},{"bransKodu":"751","bransAd":"UZUN SÜRELİ FERDİ KAZA","ay":5,"vadeGun":365},{"bransKodu":"751","bransAd":"UZUN SÜRELİ FERDİ KAZA","ay":6,"vadeGun":365},{"bransKodu":"751","bransAd":"UZUN SÜRELİ FERDİ KAZA","ay":7,"vadeGun":365},{"bransKodu":"751","bransAd":"UZUN SÜRELİ FERDİ KAZA","ay":8,"vadeGun":365},{"bransKodu":"751","bransAd":"UZUN SÜRELİ FERDİ KAZA","ay":9,"vadeGun":365},{"bransKodu":"751","bransAd":"UZUN SÜRELİ FERDİ KAZA","ay":10,"vadeGun":365},{"bransKodu":"751","bransAd":"UZUN SÜRELİ FERDİ KAZA","ay":11,"vadeGun":365},{"bransKodu":"751","bransAd":"UZUN SÜRELİ FERDİ KAZA","ay":12,"vadeGun":365},{"bransKodu":"752","bransAd":"HAVA ŞARTLARI","ay":1,"vadeGun":365},{"bransKodu":"752","bransAd":"HAVA ŞARTLARI","ay":2,"vadeGun":365},{"bransKodu":"752","bransAd":"HAVA ŞARTLARI","ay":3,"vadeGun":365},{"bransKodu":"752","bransAd":"HAVA ŞARTLARI","ay":4,"vadeGun":365},{"bransKodu":"752","bransAd":"HAVA ŞARTLARI","ay":5,"vadeGun":365},{"bransKodu":"752","bransAd":"HAVA ŞARTLARI","ay":6,"vadeGun":365},{"bransKodu":"752","bransAd":"HAVA ŞARTLARI","ay":7,"vadeGun":365},{"bransKodu":"752","bransAd":"HAVA ŞARTLARI","ay":8,"vadeGun":365},{"bransKodu":"752","bransAd":"HAVA ŞARTLARI","ay":9,"vadeGun":365},{"bransKodu":"752","bransAd":"HAVA ŞARTLARI","ay":10,"vadeGun":365},{"bransKodu":"752","bransAd":"HAVA ŞARTLARI","ay":11,"vadeGun":365},{"bransKodu":"752","bransAd":"HAVA ŞARTLARI","ay":12,"vadeGun":365},{"bransKodu":"753","bransAd":"GENEL GİDERLER","ay":1,"vadeGun":365},{"bransKodu":"753","bransAd":"GENEL GİDERLER","ay":2,"vadeGun":365},{"bransKodu":"753","bransAd":"GENEL GİDERLER","ay":3,"vadeGun":365},{"bransKodu":"753","bransAd":"GENEL GİDERLER","ay":4,"vadeGun":365},{"bransKodu":"753","bransAd":"GENEL GİDERLER","ay":5,"vadeGun":365},{"bransKodu":"753","bransAd":"GENEL GİDERLER","ay":6,"vadeGun":365},{"bransKodu":"753","bransAd":"GENEL GİDERLER","ay":7,"vadeGun":365},{"bransKodu":"753","bransAd":"GENEL GİDERLER","ay":8,"vadeGun":365},{"bransKodu":"753","bransAd":"GENEL GİDERLER","ay":9,"vadeGun":365},{"bransKodu":"753","bransAd":"GENEL GİDERLER","ay":10,"vadeGun":365},{"bransKodu":"753","bransAd":"GENEL GİDERLER","ay":11,"vadeGun":365},{"bransKodu":"753","bransAd":"GENEL GİDERLER","ay":12,"vadeGun":365},{"bransKodu":"754","bransAd":"BEKLENMEYEN TİCARİ GİDERLER","ay":1,"vadeGun":365},{"bransKodu":"754","bransAd":"BEKLENMEYEN TİCARİ GİDERLER","ay":2,"vadeGun":365},{"bransKodu":"754","bransAd":"BEKLENMEYEN TİCARİ GİDERLER","ay":3,"vadeGun":365},{"bransKodu":"754","bransAd":"BEKLENMEYEN TİCARİ GİDERLER","ay":4,"vadeGun":365},{"bransKodu":"754","bransAd":"BEKLENMEYEN TİCARİ GİDERLER","ay":5,"vadeGun":365},{"bransKodu":"754","bransAd":"BEKLENMEYEN TİCARİ GİDERLER","ay":6,"vadeGun":365},{"bransKodu":"754","bransAd":"BEKLENMEYEN TİCARİ GİDERLER","ay":7,"vadeGun":365},{"bransKodu":"754","bransAd":"BEKLENMEYEN TİCARİ GİDERLER","ay":8,"vadeGun":365},{"bransKodu":"754","bransAd":"BEKLENMEYEN TİCARİ GİDERLER","ay":9,"vadeGun":365},{"bransKodu":"754","bransAd":"BEKLENMEYEN TİCARİ GİDERLER","ay":10,"vadeGun":365},{"bransKodu":"754","bransAd":"BEKLENMEYEN TİCARİ GİDERLER","ay":11,"vadeGun":365},{"bransKodu":"754","bransAd":"BEKLENMEYEN TİCARİ GİDERLER","ay":12,"vadeGun":365},{"bransKodu":"755","bransAd":"KREDİ","ay":1,"vadeGun":365},{"bransKodu":"755","bransAd":"KREDİ","ay":2,"vadeGun":365},{"bransKodu":"755","bransAd":"KREDİ","ay":3,"vadeGun":365},{"bransKodu":"755","bransAd":"KREDİ","ay":4,"vadeGun":365},{"bransKodu":"755","bransAd":"KREDİ","ay":5,"vadeGun":365},{"bransKodu":"755","bransAd":"KREDİ","ay":6,"vadeGun":365},{"bransKodu":"755","bransAd":"KREDİ","ay":7,"vadeGun":365},{"bransKodu":"755","bransAd":"KREDİ","ay":8,"vadeGun":365},{"bransKodu":"755","bransAd":"KREDİ","ay":9,"vadeGun":365},{"bransKodu":"755","bransAd":"KREDİ","ay":10,"vadeGun":365},{"bransKodu":"755","bransAd":"KREDİ","ay":11,"vadeGun":365},{"bransKodu":"755","bransAd":"KREDİ","ay":12,"vadeGun":365},{"bransKodu":"756","bransAd":"İHRACAT KREDİ","ay":1,"vadeGun":365},{"bransKodu":"756","bransAd":"İHRACAT KREDİ","ay":2,"vadeGun":365},{"bransKodu":"756","bransAd":"İHRACAT KREDİ","ay":3,"vadeGun":365},{"bransKodu":"756","bransAd":"İHRACAT KREDİ","ay":4,"vadeGun":365},{"bransKodu":"756","bransAd":"İHRACAT KREDİ","ay":5,"vadeGun":365},{"bransKodu":"756","bransAd":"İHRACAT KREDİ","ay":6,"vadeGun":365},{"bransKodu":"756","bransAd":"İHRACAT KREDİ","ay":7,"vadeGun":365},{"bransKodu":"756","bransAd":"İHRACAT KREDİ","ay":8,"vadeGun":365},{"bransKodu":"756","bransAd":"İHRACAT KREDİ","ay":9,"vadeGun":365},{"bransKodu":"756","bransAd":"İHRACAT KREDİ","ay":10,"vadeGun":365},{"bransKodu":"756","bransAd":"İHRACAT KREDİ","ay":11,"vadeGun":365},{"bransKodu":"756","bransAd":"İHRACAT KREDİ","ay":12,"vadeGun":365},{"bransKodu":"757","bransAd":"PİYASA DEĞERİNDEKİ KAYIP","ay":1,"vadeGun":365},{"bransKodu":"757","bransAd":"PİYASA DEĞERİNDEKİ KAYIP","ay":2,"vadeGun":365},{"bransKodu":"757","bransAd":"PİYASA DEĞERİNDEKİ KAYIP","ay":3,"vadeGun":365},{"bransKodu":"757","bransAd":"PİYASA DEĞERİNDEKİ KAYIP","ay":4,"vadeGun":365},{"bransKodu":"757","bransAd":"PİYASA DEĞERİNDEKİ KAYIP","ay":5,"vadeGun":365},{"bransKodu":"757","bransAd":"PİYASA DEĞERİNDEKİ KAYIP","ay":6,"vadeGun":365},{"bransKodu":"757","bransAd":"PİYASA DEĞERİNDEKİ KAYIP","ay":7,"vadeGun":365},{"bransKodu":"757","bransAd":"PİYASA DEĞERİNDEKİ KAYIP","ay":8,"vadeGun":365},{"bransKodu":"757","bransAd":"PİYASA DEĞERİNDEKİ KAYIP","ay":9,"vadeGun":365},{"bransKodu":"757","bransAd":"PİYASA DEĞERİNDEKİ KAYIP","ay":10,"vadeGun":365},{"bransKodu":"757","bransAd":"PİYASA DEĞERİNDEKİ KAYIP","ay":11,"vadeGun":365},{"bransKodu":"757","bransAd":"PİYASA DEĞERİNDEKİ KAYIP","ay":12,"vadeGun":365},{"bransKodu":"758","bransAd":"KİRA VE GELİR KAYBI","ay":1,"vadeGun":365},{"bransKodu":"758","bransAd":"KİRA VE GELİR KAYBI","ay":2,"vadeGun":365},{"bransKodu":"758","bransAd":"KİRA VE GELİR KAYBI","ay":3,"vadeGun":365},{"bransKodu":"758","bransAd":"KİRA VE GELİR KAYBI","ay":4,"vadeGun":365},{"bransKodu":"758","bransAd":"KİRA VE GELİR KAYBI","ay":5,"vadeGun":365},{"bransKodu":"758","bransAd":"KİRA VE GELİR KAYBI","ay":6,"vadeGun":365},{"bransKodu":"758","bransAd":"KİRA VE GELİR KAYBI","ay":7,"vadeGun":365},{"bransKodu":"758","bransAd":"KİRA VE GELİR KAYBI","ay":8,"vadeGun":365},{"bransKodu":"758","bransAd":"KİRA VE GELİR KAYBI","ay":9,"vadeGun":365},{"bransKodu":"758","bransAd":"KİRA VE GELİR KAYBI","ay":10,"vadeGun":365},{"bransKodu":"758","bransAd":"KİRA VE GELİR KAYBI","ay":11,"vadeGun":365},{"bransKodu":"758","bransAd":"KİRA VE GELİR KAYBI","ay":12,"vadeGun":365},{"bransKodu":"759","bransAd":"DİĞER FİNANSAL KAYIPLAR","ay":1,"vadeGun":365},{"bransKodu":"759","bransAd":"DİĞER FİNANSAL KAYIPLAR","ay":2,"vadeGun":365},{"bransKodu":"759","bransAd":"DİĞER FİNANSAL KAYIPLAR","ay":3,"vadeGun":365},{"bransKodu":"759","bransAd":"DİĞER FİNANSAL KAYIPLAR","ay":4,"vadeGun":365},{"bransKodu":"759","bransAd":"DİĞER FİNANSAL KAYIPLAR","ay":5,"vadeGun":365},{"bransKodu":"759","bransAd":"DİĞER FİNANSAL KAYIPLAR","ay":6,"vadeGun":365},{"bransKodu":"759","bransAd":"DİĞER FİNANSAL KAYIPLAR","ay":7,"vadeGun":365},{"bransKodu":"759","bransAd":"DİĞER FİNANSAL KAYIPLAR","ay":8,"vadeGun":365},{"bransKodu":"759","bransAd":"DİĞER FİNANSAL KAYIPLAR","ay":9,"vadeGun":365},{"bransKodu":"759","bransAd":"DİĞER FİNANSAL KAYIPLAR","ay":10,"vadeGun":365},{"bransKodu":"759","bransAd":"DİĞER FİNANSAL KAYIPLAR","ay":11,"vadeGun":365},{"bransKodu":"759","bransAd":"DİĞER FİNANSAL KAYIPLAR","ay":12,"vadeGun":365},{"bransKodu":"760","bransAd":"HUKUKSAL KORUMA","ay":1,"vadeGun":363.762593},{"bransKodu":"760","bransAd":"HUKUKSAL KORUMA","ay":2,"vadeGun":364.720296},{"bransKodu":"760","bransAd":"HUKUKSAL KORUMA","ay":3,"vadeGun":363.794369},{"bransKodu":"760","bransAd":"HUKUKSAL KORUMA","ay":4,"vadeGun":361.553298},{"bransKodu":"760","bransAd":"HUKUKSAL KORUMA","ay":5,"vadeGun":361.090953},{"bransKodu":"760","bransAd":"HUKUKSAL KORUMA","ay":6,"vadeGun":354.622054},{"bransKodu":"760","bransAd":"HUKUKSAL KORUMA","ay":7,"vadeGun":355.388482},{"bransKodu":"760","bransAd":"HUKUKSAL KORUMA","ay":8,"vadeGun":360.941222},{"bransKodu":"760","bransAd":"HUKUKSAL KORUMA","ay":9,"vadeGun":359.505172},{"bransKodu":"760","bransAd":"HUKUKSAL KORUMA","ay":10,"vadeGun":361.302533},{"bransKodu":"760","bransAd":"HUKUKSAL KORUMA","ay":11,"vadeGun":362.271982},{"bransKodu":"760","bransAd":"HUKUKSAL KORUMA","ay":12,"vadeGun":363.49895},{"bransKodu":"761","bransAd":"PATLAMA","ay":1,"vadeGun":365},{"bransKodu":"761","bransAd":"PATLAMA","ay":2,"vadeGun":365},{"bransKodu":"761","bransAd":"PATLAMA","ay":3,"vadeGun":365},{"bransKodu":"761","bransAd":"PATLAMA","ay":4,"vadeGun":365},{"bransKodu":"761","bransAd":"PATLAMA","ay":5,"vadeGun":365},{"bransKodu":"761","bransAd":"PATLAMA","ay":6,"vadeGun":365},{"bransKodu":"761","bransAd":"PATLAMA","ay":7,"vadeGun":365},{"bransKodu":"761","bransAd":"PATLAMA","ay":8,"vadeGun":365},{"bransKodu":"761","bransAd":"PATLAMA","ay":9,"vadeGun":365},{"bransKodu":"761","bransAd":"PATLAMA","ay":10,"vadeGun":365},{"bransKodu":"761","bransAd":"PATLAMA","ay":11,"vadeGun":365},{"bransKodu":"761","bransAd":"PATLAMA","ay":12,"vadeGun":365},{"bransKodu":"765","bransAd":"MAKİNE KIRILMASI","ay":1,"vadeGun":359.443045},{"bransKodu":"765","bransAd":"MAKİNE KIRILMASI","ay":2,"vadeGun":365.86648},{"bransKodu":"765","bransAd":"MAKİNE KIRILMASI","ay":3,"vadeGun":366.917126},{"bransKodu":"765","bransAd":"MAKİNE KIRILMASI","ay":4,"vadeGun":370.476303},{"bransKodu":"765","bransAd":"MAKİNE KIRILMASI","ay":5,"vadeGun":368.81448},{"bransKodu":"765","bransAd":"MAKİNE KIRILMASI","ay":6,"vadeGun":366.294306},{"bransKodu":"765","bransAd":"MAKİNE KIRILMASI","ay":7,"vadeGun":372.899464},{"bransKodu":"765","bransAd":"MAKİNE KIRILMASI","ay":8,"vadeGun":372.438418},{"bransKodu":"765","bransAd":"MAKİNE KIRILMASI","ay":9,"vadeGun":363.032964},{"bransKodu":"765","bransAd":"MAKİNE KIRILMASI","ay":10,"vadeGun":369.761691},{"bransKodu":"765","bransAd":"MAKİNE KIRILMASI","ay":11,"vadeGun":361.789324},{"bransKodu":"765","bransAd":"MAKİNE KIRILMASI","ay":12,"vadeGun":366.123939},{"bransKodu":"766","bransAd":"MONTAJ","ay":1,"vadeGun":365},{"bransKodu":"766","bransAd":"MONTAJ","ay":2,"vadeGun":365},{"bransKodu":"766","bransAd":"MONTAJ","ay":3,"vadeGun":365},{"bransKodu":"766","bransAd":"MONTAJ","ay":4,"vadeGun":365},{"bransKodu":"766","bransAd":"MONTAJ","ay":5,"vadeGun":365},{"bransKodu":"766","bransAd":"MONTAJ","ay":6,"vadeGun":365},{"bransKodu":"766","bransAd":"MONTAJ","ay":7,"vadeGun":365},{"bransKodu":"766","bransAd":"MONTAJ","ay":8,"vadeGun":365},{"bransKodu":"766","bransAd":"MONTAJ","ay":9,"vadeGun":365},{"bransKodu":"766","bransAd":"MONTAJ","ay":10,"vadeGun":365},{"bransKodu":"766","bransAd":"MONTAJ","ay":11,"vadeGun":365},{"bransKodu":"766","bransAd":"MONTAJ","ay":12,"vadeGun":365},{"bransKodu":"767","bransAd":"İNŞAAT","ay":1,"vadeGun":290.140301},{"bransKodu":"767","bransAd":"İNŞAAT","ay":2,"vadeGun":270.177579},{"bransKodu":"767","bransAd":"İNŞAAT","ay":3,"vadeGun":216.473592},{"bransKodu":"767","bransAd":"İNŞAAT","ay":4,"vadeGun":211.487427},{"bransKodu":"767","bransAd":"İNŞAAT","ay":5,"vadeGun":162.558922},{"bransKodu":"767","bransAd":"İNŞAAT","ay":6,"vadeGun":208.596441},{"bransKodu":"767","bransAd":"İNŞAAT","ay":7,"vadeGun":158.118593},{"bransKodu":"767","bransAd":"İNŞAAT","ay":8,"vadeGun":161.142173},{"bransKodu":"767","bransAd":"İNŞAAT","ay":9,"vadeGun":164.409691},{"bransKodu":"767","bransAd":"İNŞAAT","ay":10,"vadeGun":163.74563},{"bransKodu":"767","bransAd":"İNŞAAT","ay":11,"vadeGun":157.196812},{"bransKodu":"767","bransAd":"İNŞAAT","ay":12,"vadeGun":168.318311},{"bransKodu":"768","bransAd":"ELEKTRONİK CİHAZ","ay":1,"vadeGun":353.609518},{"bransKodu":"768","bransAd":"ELEKTRONİK CİHAZ","ay":2,"vadeGun":363.53451},{"bransKodu":"768","bransAd":"ELEKTRONİK CİHAZ","ay":3,"vadeGun":359.722986},{"bransKodu":"768","bransAd":"ELEKTRONİK CİHAZ","ay":4,"vadeGun":360.48093},{"bransKodu":"768","bransAd":"ELEKTRONİK CİHAZ","ay":5,"vadeGun":355.671703},{"bransKodu":"768","bransAd":"ELEKTRONİK CİHAZ","ay":6,"vadeGun":356.153295},{"bransKodu":"768","bransAd":"ELEKTRONİK CİHAZ","ay":7,"vadeGun":360.511907},{"bransKodu":"768","bransAd":"ELEKTRONİK CİHAZ","ay":8,"vadeGun":355.254329},{"bransKodu":"768","bransAd":"ELEKTRONİK CİHAZ","ay":9,"vadeGun":341.836912},{"bransKodu":"768","bransAd":"ELEKTRONİK CİHAZ","ay":10,"vadeGun":336.766012},{"bransKodu":"768","bransAd":"ELEKTRONİK CİHAZ","ay":11,"vadeGun":344.599381},{"bransKodu":"768","bransAd":"ELEKTRONİK CİHAZ","ay":12,"vadeGun":344.728769},{"bransKodu":"769","bransAd":"YAPI DENETİMİ ZORUNLU MALİ SORUMLULUK","ay":1,"vadeGun":365},{"bransKodu":"769","bransAd":"YAPI DENETİMİ ZORUNLU MALİ SORUMLULUK","ay":2,"vadeGun":365},{"bransKodu":"769","bransAd":"YAPI DENETİMİ ZORUNLU MALİ SORUMLULUK","ay":3,"vadeGun":365},{"bransKodu":"769","bransAd":"YAPI DENETİMİ ZORUNLU MALİ SORUMLULUK","ay":4,"vadeGun":365},{"bransKodu":"769","bransAd":"YAPI DENETİMİ ZORUNLU MALİ SORUMLULUK","ay":5,"vadeGun":365},{"bransKodu":"769","bransAd":"YAPI DENETİMİ ZORUNLU MALİ SORUMLULUK","ay":6,"vadeGun":365},{"bransKodu":"769","bransAd":"YAPI DENETİMİ ZORUNLU MALİ SORUMLULUK","ay":7,"vadeGun":365},{"bransKodu":"769","bransAd":"YAPI DENETİMİ ZORUNLU MALİ SORUMLULUK","ay":8,"vadeGun":365},{"bransKodu":"769","bransAd":"YAPI DENETİMİ ZORUNLU MALİ SORUMLULUK","ay":9,"vadeGun":365},{"bransKodu":"769","bransAd":"YAPI DENETİMİ ZORUNLU MALİ SORUMLULUK","ay":10,"vadeGun":365},{"bransKodu":"769","bransAd":"YAPI DENETİMİ ZORUNLU MALİ SORUMLULUK","ay":11,"vadeGun":365},{"bransKodu":"769","bransAd":"YAPI DENETİMİ ZORUNLU MALİ SORUMLULUK","ay":12,"vadeGun":365},{"bransKodu":"770","bransAd":"DENİZ YOLU TAŞIMACILIĞI ZMM","ay":1,"vadeGun":365},{"bransKodu":"770","bransAd":"DENİZ YOLU TAŞIMACILIĞI ZMM","ay":2,"vadeGun":365},{"bransKodu":"770","bransAd":"DENİZ YOLU TAŞIMACILIĞI ZMM","ay":3,"vadeGun":365},{"bransKodu":"770","bransAd":"DENİZ YOLU TAŞIMACILIĞI ZMM","ay":4,"vadeGun":365},{"bransKodu":"770","bransAd":"DENİZ YOLU TAŞIMACILIĞI ZMM","ay":5,"vadeGun":365},{"bransKodu":"770","bransAd":"DENİZ YOLU TAŞIMACILIĞI ZMM","ay":6,"vadeGun":365},{"bransKodu":"770","bransAd":"DENİZ YOLU TAŞIMACILIĞI ZMM","ay":7,"vadeGun":365},{"bransKodu":"770","bransAd":"DENİZ YOLU TAŞIMACILIĞI ZMM","ay":8,"vadeGun":365},{"bransKodu":"770","bransAd":"DENİZ YOLU TAŞIMACILIĞI ZMM","ay":9,"vadeGun":365},{"bransKodu":"770","bransAd":"DENİZ YOLU TAŞIMACILIĞI ZMM","ay":10,"vadeGun":365},{"bransKodu":"770","bransAd":"DENİZ YOLU TAŞIMACILIĞI ZMM","ay":11,"vadeGun":365},{"bransKodu":"770","bransAd":"DENİZ YOLU TAŞIMACILIĞI ZMM","ay":12,"vadeGun":365},{"bransKodu":"771","bransAd":"ÜRÜN SORUMLULUK","ay":1,"vadeGun":365},{"bransKodu":"771","bransAd":"ÜRÜN SORUMLULUK","ay":2,"vadeGun":365},{"bransKodu":"771","bransAd":"ÜRÜN SORUMLULUK","ay":3,"vadeGun":365},{"bransKodu":"771","bransAd":"ÜRÜN SORUMLULUK","ay":4,"vadeGun":365},{"bransKodu":"771","bransAd":"ÜRÜN SORUMLULUK","ay":5,"vadeGun":365},{"bransKodu":"771","bransAd":"ÜRÜN SORUMLULUK","ay":6,"vadeGun":365},{"bransKodu":"771","bransAd":"ÜRÜN SORUMLULUK","ay":7,"vadeGun":365},{"bransKodu":"771","bransAd":"ÜRÜN SORUMLULUK","ay":8,"vadeGun":365},{"bransKodu":"771","bransAd":"ÜRÜN SORUMLULUK","ay":9,"vadeGun":365},{"bransKodu":"771","bransAd":"ÜRÜN SORUMLULUK","ay":10,"vadeGun":365},{"bransKodu":"771","bransAd":"ÜRÜN SORUMLULUK","ay":11,"vadeGun":365},{"bransKodu":"771","bransAd":"ÜRÜN SORUMLULUK","ay":12,"vadeGun":365},{"bransKodu":"773","bransAd":"DEVLET DESTEKLİ ARICILIK","ay":1,"vadeGun":365.333333},{"bransKodu":"773","bransAd":"DEVLET DESTEKLİ ARICILIK","ay":2,"vadeGun":365.127168},{"bransKodu":"773","bransAd":"DEVLET DESTEKLİ ARICILIK","ay":3,"vadeGun":365.333333},{"bransKodu":"773","bransAd":"DEVLET DESTEKLİ ARICILIK","ay":4,"vadeGun":365.333333},{"bransKodu":"773","bransAd":"DEVLET DESTEKLİ ARICILIK","ay":5,"vadeGun":365.333333},{"bransKodu":"773","bransAd":"DEVLET DESTEKLİ ARICILIK","ay":6,"vadeGun":365.333333},{"bransKodu":"773","bransAd":"DEVLET DESTEKLİ ARICILIK","ay":7,"vadeGun":365.333333},{"bransKodu":"773","bransAd":"DEVLET DESTEKLİ ARICILIK","ay":8,"vadeGun":365.333333},{"bransKodu":"773","bransAd":"DEVLET DESTEKLİ ARICILIK","ay":9,"vadeGun":365.333333},{"bransKodu":"773","bransAd":"DEVLET DESTEKLİ ARICILIK","ay":10,"vadeGun":365.333333},{"bransKodu":"773","bransAd":"DEVLET DESTEKLİ ARICILIK","ay":11,"vadeGun":365.333333},{"bransKodu":"773","bransAd":"DEVLET DESTEKLİ ARICILIK","ay":12,"vadeGun":365.333333},{"bransKodu":"774","bransAd":"SU ÜRÜNLERİ","ay":1,"vadeGun":365},{"bransKodu":"774","bransAd":"SU ÜRÜNLERİ","ay":2,"vadeGun":365},{"bransKodu":"774","bransAd":"SU ÜRÜNLERİ","ay":3,"vadeGun":365},{"bransKodu":"774","bransAd":"SU ÜRÜNLERİ","ay":4,"vadeGun":365},{"bransKodu":"774","bransAd":"SU ÜRÜNLERİ","ay":5,"vadeGun":365},{"bransKodu":"774","bransAd":"SU ÜRÜNLERİ","ay":6,"vadeGun":365},{"bransKodu":"774","bransAd":"SU ÜRÜNLERİ","ay":7,"vadeGun":365},{"bransKodu":"774","bransAd":"SU ÜRÜNLERİ","ay":8,"vadeGun":365},{"bransKodu":"774","bransAd":"SU ÜRÜNLERİ","ay":9,"vadeGun":365},{"bransKodu":"774","bransAd":"SU ÜRÜNLERİ","ay":10,"vadeGun":365},{"bransKodu":"774","bransAd":"SU ÜRÜNLERİ","ay":11,"vadeGun":365},{"bransKodu":"774","bransAd":"SU ÜRÜNLERİ","ay":12,"vadeGun":365},{"bransKodu":"775","bransAd":"DOLU SERA","ay":1,"vadeGun":365},{"bransKodu":"775","bransAd":"DOLU SERA","ay":2,"vadeGun":365},{"bransKodu":"775","bransAd":"DOLU SERA","ay":3,"vadeGun":365},{"bransKodu":"775","bransAd":"DOLU SERA","ay":4,"vadeGun":365},{"bransKodu":"775","bransAd":"DOLU SERA","ay":5,"vadeGun":365},{"bransKodu":"775","bransAd":"DOLU SERA","ay":6,"vadeGun":365},{"bransKodu":"775","bransAd":"DOLU SERA","ay":7,"vadeGun":365},{"bransKodu":"775","bransAd":"DOLU SERA","ay":8,"vadeGun":365},{"bransKodu":"775","bransAd":"DOLU SERA","ay":9,"vadeGun":365},{"bransKodu":"775","bransAd":"DOLU SERA","ay":10,"vadeGun":365},{"bransKodu":"775","bransAd":"DOLU SERA","ay":11,"vadeGun":365},{"bransKodu":"775","bransAd":"DOLU SERA","ay":12,"vadeGun":365},{"bransKodu":"776","bransAd":"DEVLET DESTEKLİ SERA","ay":1,"vadeGun":365.333333},{"bransKodu":"776","bransAd":"DEVLET DESTEKLİ SERA","ay":2,"vadeGun":365.340156},{"bransKodu":"776","bransAd":"DEVLET DESTEKLİ SERA","ay":3,"vadeGun":365.333333},{"bransKodu":"776","bransAd":"DEVLET DESTEKLİ SERA","ay":4,"vadeGun":365.333333},{"bransKodu":"776","bransAd":"DEVLET DESTEKLİ SERA","ay":5,"vadeGun":365.333333},{"bransKodu":"776","bransAd":"DEVLET DESTEKLİ SERA","ay":6,"vadeGun":365.333333},{"bransKodu":"776","bransAd":"DEVLET DESTEKLİ SERA","ay":7,"vadeGun":365.333333},{"bransKodu":"776","bransAd":"DEVLET DESTEKLİ SERA","ay":8,"vadeGun":365.333333},{"bransKodu":"776","bransAd":"DEVLET DESTEKLİ SERA","ay":9,"vadeGun":365.333333},{"bransKodu":"776","bransAd":"DEVLET DESTEKLİ SERA","ay":10,"vadeGun":365.333333},{"bransKodu":"776","bransAd":"DEVLET DESTEKLİ SERA","ay":11,"vadeGun":365.333333},{"bransKodu":"776","bransAd":"DEVLET DESTEKLİ SERA","ay":12,"vadeGun":365.333333},{"bransKodu":"777","bransAd":"DEVLET DESTEKLİ BİTKİSEL ÜRÜN","ay":1,"vadeGun":213.632089},{"bransKodu":"777","bransAd":"DEVLET DESTEKLİ BİTKİSEL ÜRÜN","ay":2,"vadeGun":188.172211},{"bransKodu":"777","bransAd":"DEVLET DESTEKLİ BİTKİSEL ÜRÜN","ay":3,"vadeGun":168.456834},{"bransKodu":"777","bransAd":"DEVLET DESTEKLİ BİTKİSEL ÜRÜN","ay":4,"vadeGun":146.755294},{"bransKodu":"777","bransAd":"DEVLET DESTEKLİ BİTKİSEL ÜRÜN","ay":5,"vadeGun":153.812785},{"bransKodu":"777","bransAd":"DEVLET DESTEKLİ BİTKİSEL ÜRÜN","ay":6,"vadeGun":159.326677},{"bransKodu":"777","bransAd":"DEVLET DESTEKLİ BİTKİSEL ÜRÜN","ay":7,"vadeGun":187.716165},{"bransKodu":"777","bransAd":"DEVLET DESTEKLİ BİTKİSEL ÜRÜN","ay":8,"vadeGun":229.062871},{"bransKodu":"777","bransAd":"DEVLET DESTEKLİ BİTKİSEL ÜRÜN","ay":9,"vadeGun":283.531489},{"bransKodu":"777","bransAd":"DEVLET DESTEKLİ BİTKİSEL ÜRÜN","ay":10,"vadeGun":314.497387},{"bransKodu":"777","bransAd":"DEVLET DESTEKLİ BİTKİSEL ÜRÜN","ay":11,"vadeGun":269.14027},{"bransKodu":"777","bransAd":"DEVLET DESTEKLİ BİTKİSEL ÜRÜN","ay":12,"vadeGun":240.745319},{"bransKodu":"778","bransAd":"DEVLET DESTEKLİ SU ÜRÜNLERİ","ay":1,"vadeGun":287},{"bransKodu":"778","bransAd":"DEVLET DESTEKLİ SU ÜRÜNLERİ","ay":2,"vadeGun":366},{"bransKodu":"778","bransAd":"DEVLET DESTEKLİ SU ÜRÜNLERİ","ay":3,"vadeGun":226},{"bransKodu":"778","bransAd":"DEVLET DESTEKLİ SU ÜRÜNLERİ","ay":4,"vadeGun":271},{"bransKodu":"778","bransAd":"DEVLET DESTEKLİ SU ÜRÜNLERİ","ay":5,"vadeGun":290},{"bransKodu":"778","bransAd":"DEVLET DESTEKLİ SU ÜRÜNLERİ","ay":6,"vadeGun":365},{"bransKodu":"778","bransAd":"DEVLET DESTEKLİ SU ÜRÜNLERİ","ay":7,"vadeGun":365},{"bransKodu":"778","bransAd":"DEVLET DESTEKLİ SU ÜRÜNLERİ","ay":8,"vadeGun":306},{"bransKodu":"778","bransAd":"DEVLET DESTEKLİ SU ÜRÜNLERİ","ay":9,"vadeGun":365},{"bransKodu":"778","bransAd":"DEVLET DESTEKLİ SU ÜRÜNLERİ","ay":10,"vadeGun":365.5},{"bransKodu":"778","bransAd":"DEVLET DESTEKLİ SU ÜRÜNLERİ","ay":11,"vadeGun":365},{"bransKodu":"778","bransAd":"DEVLET DESTEKLİ SU ÜRÜNLERİ","ay":12,"vadeGun":341.733333},{"bransKodu":"779","bransAd":"DEVLET DESTEKLİ HAYVAN HAYAT","ay":1,"vadeGun":363.131559},{"bransKodu":"779","bransAd":"DEVLET DESTEKLİ HAYVAN HAYAT","ay":2,"vadeGun":365.05579},{"bransKodu":"779","bransAd":"DEVLET DESTEKLİ HAYVAN HAYAT","ay":3,"vadeGun":363.774004},{"bransKodu":"779","bransAd":"DEVLET DESTEKLİ HAYVAN HAYAT","ay":4,"vadeGun":363.992519},{"bransKodu":"779","bransAd":"DEVLET DESTEKLİ HAYVAN HAYAT","ay":5,"vadeGun":364.204275},{"bransKodu":"779","bransAd":"DEVLET DESTEKLİ HAYVAN HAYAT","ay":6,"vadeGun":365.930883},{"bransKodu":"779","bransAd":"DEVLET DESTEKLİ HAYVAN HAYAT","ay":7,"vadeGun":367.306438},{"bransKodu":"779","bransAd":"DEVLET DESTEKLİ HAYVAN HAYAT","ay":8,"vadeGun":367.717579},{"bransKodu":"779","bransAd":"DEVLET DESTEKLİ HAYVAN HAYAT","ay":9,"vadeGun":365.267519},{"bransKodu":"779","bransAd":"DEVLET DESTEKLİ HAYVAN HAYAT","ay":10,"vadeGun":363.696801},{"bransKodu":"779","bransAd":"DEVLET DESTEKLİ HAYVAN HAYAT","ay":11,"vadeGun":364.36134},{"bransKodu":"779","bransAd":"DEVLET DESTEKLİ HAYVAN HAYAT","ay":12,"vadeGun":365.473464},{"bransKodu":"780","bransAd":"HAYVAN HAYAT","ay":1,"vadeGun":365},{"bransKodu":"780","bransAd":"HAYVAN HAYAT","ay":2,"vadeGun":365},{"bransKodu":"780","bransAd":"HAYVAN HAYAT","ay":3,"vadeGun":365},{"bransKodu":"780","bransAd":"HAYVAN HAYAT","ay":4,"vadeGun":365},{"bransKodu":"780","bransAd":"HAYVAN HAYAT","ay":5,"vadeGun":365},{"bransKodu":"780","bransAd":"HAYVAN HAYAT","ay":6,"vadeGun":365},{"bransKodu":"780","bransAd":"HAYVAN HAYAT","ay":7,"vadeGun":365},{"bransKodu":"780","bransAd":"HAYVAN HAYAT","ay":8,"vadeGun":365},{"bransKodu":"780","bransAd":"HAYVAN HAYAT","ay":9,"vadeGun":365},{"bransKodu":"780","bransAd":"HAYVAN HAYAT","ay":10,"vadeGun":365},{"bransKodu":"780","bransAd":"HAYVAN HAYAT","ay":11,"vadeGun":365},{"bransKodu":"780","bransAd":"HAYVAN HAYAT","ay":12,"vadeGun":365},{"bransKodu":"781","bransAd":"KÜMES HAYVAN HAYAT","ay":1,"vadeGun":365},{"bransKodu":"781","bransAd":"KÜMES HAYVAN HAYAT","ay":2,"vadeGun":365},{"bransKodu":"781","bransAd":"KÜMES HAYVAN HAYAT","ay":3,"vadeGun":365},{"bransKodu":"781","bransAd":"KÜMES HAYVAN HAYAT","ay":4,"vadeGun":365},{"bransKodu":"781","bransAd":"KÜMES HAYVAN HAYAT","ay":5,"vadeGun":365},{"bransKodu":"781","bransAd":"KÜMES HAYVAN HAYAT","ay":6,"vadeGun":365},{"bransKodu":"781","bransAd":"KÜMES HAYVAN HAYAT","ay":7,"vadeGun":365},{"bransKodu":"781","bransAd":"KÜMES HAYVAN HAYAT","ay":8,"vadeGun":365},{"bransKodu":"781","bransAd":"KÜMES HAYVAN HAYAT","ay":9,"vadeGun":365},{"bransKodu":"781","bransAd":"KÜMES HAYVAN HAYAT","ay":10,"vadeGun":365},{"bransKodu":"781","bransAd":"KÜMES HAYVAN HAYAT","ay":11,"vadeGun":365},{"bransKodu":"781","bransAd":"KÜMES HAYVAN HAYAT","ay":12,"vadeGun":365},{"bransKodu":"782","bransAd":"DEVLET DESTEKLİ KÜMES HAYVAN HAYAT","ay":1,"vadeGun":365.333333},{"bransKodu":"782","bransAd":"DEVLET DESTEKLİ KÜMES HAYVAN HAYAT","ay":2,"vadeGun":365.333333},{"bransKodu":"782","bransAd":"DEVLET DESTEKLİ KÜMES HAYVAN HAYAT","ay":3,"vadeGun":352},{"bransKodu":"782","bransAd":"DEVLET DESTEKLİ KÜMES HAYVAN HAYAT","ay":4,"vadeGun":285.333333},{"bransKodu":"782","bransAd":"DEVLET DESTEKLİ KÜMES HAYVAN HAYAT","ay":5,"vadeGun":266.086957},{"bransKodu":"782","bransAd":"DEVLET DESTEKLİ KÜMES HAYVAN HAYAT","ay":6,"vadeGun":365.333333},{"bransKodu":"782","bransAd":"DEVLET DESTEKLİ KÜMES HAYVAN HAYAT","ay":7,"vadeGun":363.111111},{"bransKodu":"782","bransAd":"DEVLET DESTEKLİ KÜMES HAYVAN HAYAT","ay":8,"vadeGun":362.108971},{"bransKodu":"782","bransAd":"DEVLET DESTEKLİ KÜMES HAYVAN HAYAT","ay":9,"vadeGun":361.358178},{"bransKodu":"782","bransAd":"DEVLET DESTEKLİ KÜMES HAYVAN HAYAT","ay":10,"vadeGun":368.215167},{"bransKodu":"782","bransAd":"DEVLET DESTEKLİ KÜMES HAYVAN HAYAT","ay":11,"vadeGun":365.333333},{"bransKodu":"782","bransAd":"DEVLET DESTEKLİ KÜMES HAYVAN HAYAT","ay":12,"vadeGun":364.161172},{"bransKodu":"783","bransAd":"DEVLET DESTEKLİ KÜÇÜKBAŞ HAYVAN HAYAT","ay":1,"vadeGun":367.670712},{"bransKodu":"783","bransAd":"DEVLET DESTEKLİ KÜÇÜKBAŞ HAYVAN HAYAT","ay":2,"vadeGun":367.916512},{"bransKodu":"783","bransAd":"DEVLET DESTEKLİ KÜÇÜKBAŞ HAYVAN HAYAT","ay":3,"vadeGun":367.678033},{"bransKodu":"783","bransAd":"DEVLET DESTEKLİ KÜÇÜKBAŞ HAYVAN HAYAT","ay":4,"vadeGun":368.359775},{"bransKodu":"783","bransAd":"DEVLET DESTEKLİ KÜÇÜKBAŞ HAYVAN HAYAT","ay":5,"vadeGun":369.384819},{"bransKodu":"783","bransAd":"DEVLET DESTEKLİ KÜÇÜKBAŞ HAYVAN HAYAT","ay":6,"vadeGun":371.167273},{"bransKodu":"783","bransAd":"DEVLET DESTEKLİ KÜÇÜKBAŞ HAYVAN HAYAT","ay":7,"vadeGun":371.817555},{"bransKodu":"783","bransAd":"DEVLET DESTEKLİ KÜÇÜKBAŞ HAYVAN HAYAT","ay":8,"vadeGun":370.319474},{"bransKodu":"783","bransAd":"DEVLET DESTEKLİ KÜÇÜKBAŞ HAYVAN HAYAT","ay":9,"vadeGun":369.702557},{"bransKodu":"783","bransAd":"DEVLET DESTEKLİ KÜÇÜKBAŞ HAYVAN HAYAT","ay":10,"vadeGun":371.443174},{"bransKodu":"783","bransAd":"DEVLET DESTEKLİ KÜÇÜKBAŞ HAYVAN HAYAT","ay":11,"vadeGun":369.556583},{"bransKodu":"783","bransAd":"DEVLET DESTEKLİ KÜÇÜKBAŞ HAYVAN HAYAT","ay":12,"vadeGun":368.019454},{"bransKodu":"784","bransAd":"HASTALIK","ay":1,"vadeGun":365.333333},{"bransKodu":"784","bransAd":"HASTALIK","ay":2,"vadeGun":365.333333},{"bransKodu":"784","bransAd":"HASTALIK","ay":3,"vadeGun":365.333333},{"bransKodu":"784","bransAd":"HASTALIK","ay":4,"vadeGun":365.333333},{"bransKodu":"784","bransAd":"HASTALIK","ay":5,"vadeGun":365.333333},{"bransKodu":"784","bransAd":"HASTALIK","ay":6,"vadeGun":365.333333},{"bransKodu":"784","bransAd":"HASTALIK","ay":7,"vadeGun":365.333333},{"bransKodu":"784","bransAd":"HASTALIK","ay":8,"vadeGun":365.333333},{"bransKodu":"784","bransAd":"HASTALIK","ay":9,"vadeGun":365.333333},{"bransKodu":"784","bransAd":"HASTALIK","ay":10,"vadeGun":365.333333},{"bransKodu":"784","bransAd":"HASTALIK","ay":11,"vadeGun":365.5},{"bransKodu":"784","bransAd":"HASTALIK","ay":12,"vadeGun":365.333333},{"bransKodu":"785","bransAd":"SAĞLIK","ay":1,"vadeGun":365.299936},{"bransKodu":"785","bransAd":"SAĞLIK","ay":2,"vadeGun":356.93188},{"bransKodu":"785","bransAd":"SAĞLIK","ay":3,"vadeGun":357.014269},{"bransKodu":"785","bransAd":"SAĞLIK","ay":4,"vadeGun":331.557196},{"bransKodu":"785","bransAd":"SAĞLIK","ay":5,"vadeGun":349.624578},{"bransKodu":"785","bransAd":"SAĞLIK","ay":6,"vadeGun":308.410311},{"bransKodu":"785","bransAd":"SAĞLIK","ay":7,"vadeGun":330.506106},{"bransKodu":"785","bransAd":"SAĞLIK","ay":8,"vadeGun":255.364266},{"bransKodu":"785","bransAd":"SAĞLIK","ay":9,"vadeGun":279.356773},{"bransKodu":"785","bransAd":"SAĞLIK","ay":10,"vadeGun":256.030301},{"bransKodu":"785","bransAd":"SAĞLIK","ay":11,"vadeGun":348.537146},{"bransKodu":"785","bransAd":"SAĞLIK","ay":12,"vadeGun":357.209658},{"bransKodu":"786","bransAd":"SEYAHAT SAĞLIK","ay":1,"vadeGun":38.87037},{"bransKodu":"786","bransAd":"SEYAHAT SAĞLIK","ay":2,"vadeGun":44.288236},{"bransKodu":"786","bransAd":"SEYAHAT SAĞLIK","ay":3,"vadeGun":34.254323},{"bransKodu":"786","bransAd":"SEYAHAT SAĞLIK","ay":4,"vadeGun":27.742295},{"bransKodu":"786","bransAd":"SEYAHAT SAĞLIK","ay":5,"vadeGun":49.542054},{"bransKodu":"786","bransAd":"SEYAHAT SAĞLIK","ay":6,"vadeGun":44.263039},{"bransKodu":"786","bransAd":"SEYAHAT SAĞLIK","ay":7,"vadeGun":47.968101},{"bransKodu":"786","bransAd":"SEYAHAT SAĞLIK","ay":8,"vadeGun":51.849968},{"bransKodu":"786","bransAd":"SEYAHAT SAĞLIK","ay":9,"vadeGun":58.723664},{"bransKodu":"786","bransAd":"SEYAHAT SAĞLIK","ay":10,"vadeGun":28.646169},{"bransKodu":"786","bransAd":"SEYAHAT SAĞLIK","ay":11,"vadeGun":41.087815},{"bransKodu":"786","bransAd":"SEYAHAT SAĞLIK","ay":12,"vadeGun":44.612355},{"bransKodu":"789","bransAd":"SEYAHAT ARAÇ DESTEK","ay":1,"vadeGun":365},{"bransKodu":"789","bransAd":"SEYAHAT ARAÇ DESTEK","ay":2,"vadeGun":365},{"bransKodu":"789","bransAd":"SEYAHAT ARAÇ DESTEK","ay":3,"vadeGun":365},{"bransKodu":"789","bransAd":"SEYAHAT ARAÇ DESTEK","ay":4,"vadeGun":365},{"bransKodu":"789","bransAd":"SEYAHAT ARAÇ DESTEK","ay":5,"vadeGun":365},{"bransKodu":"789","bransAd":"SEYAHAT ARAÇ DESTEK","ay":6,"vadeGun":365},{"bransKodu":"789","bransAd":"SEYAHAT ARAÇ DESTEK","ay":7,"vadeGun":365},{"bransKodu":"789","bransAd":"SEYAHAT ARAÇ DESTEK","ay":8,"vadeGun":365},{"bransKodu":"789","bransAd":"SEYAHAT ARAÇ DESTEK","ay":9,"vadeGun":365},{"bransKodu":"789","bransAd":"SEYAHAT ARAÇ DESTEK","ay":10,"vadeGun":365},{"bransKodu":"789","bransAd":"SEYAHAT ARAÇ DESTEK","ay":11,"vadeGun":365},{"bransKodu":"789","bransAd":"SEYAHAT ARAÇ DESTEK","ay":12,"vadeGun":365},{"bransKodu":"798","bransAd":"DESTEK","ay":1,"vadeGun":365},{"bransKodu":"798","bransAd":"DESTEK","ay":2,"vadeGun":365},{"bransKodu":"798","bransAd":"DESTEK","ay":3,"vadeGun":365},{"bransKodu":"798","bransAd":"DESTEK","ay":4,"vadeGun":365},{"bransKodu":"798","bransAd":"DESTEK","ay":5,"vadeGun":365},{"bransKodu":"798","bransAd":"DESTEK","ay":6,"vadeGun":365},{"bransKodu":"798","bransAd":"DESTEK","ay":7,"vadeGun":365},{"bransKodu":"798","bransAd":"DESTEK","ay":8,"vadeGun":365},{"bransKodu":"798","bransAd":"DESTEK","ay":9,"vadeGun":365},{"bransKodu":"798","bransAd":"DESTEK","ay":10,"vadeGun":365},{"bransKodu":"798","bransAd":"DESTEK","ay":11,"vadeGun":365},{"bransKodu":"798","bransAd":"DESTEK","ay":12,"vadeGun":365}]